Workbook

Sheet Assumptions
B1: MemoryCharm Financial Model — Assumptions
B2: Yellow cells are editable — change them to see impact on Projections & Summary sheets
B4: CHARM PRICING (Retail to Consumer)
B5: Tier | C5: Unit Price | D5: COGS / Unit | E5: Gross Margin
B6: 10-Year Charm | C6: 29.99 | D6: 8.5 | E6: =C6-D6 -> 21.49
B7: 15-Year Charm | C7: 44.99 | D7: 8.5 | E7: =C7-D7 -> 36.49
B8: Retail (Perpetual) Charm | C8: 69.99 | D8: 9 | E8: =C8-D8 -> 60.99
B10: UPSELL / ADD-ON PRICING
B11: Product | C11: Price | D11: Cost | E11: Margin
B12: Extend Memory (+5 years) | C12: 14.99 | D12: 1 | E12: =C12-D12 -> 13.99
B13: Upgrade Tier (avg revenue per upgrade) | C13: 19.99 | D13: 0.5 | E13: =C13-D13 -> 19.49
B14: Gift Wrap | C14: 4.99 | D14: 1.5 | E14: =C14-D14 -> 3.49
B16: MONTHLY UNIT SALES (Starting Month 1)
B17: Item | C17: Units / Month | D17: MoM Growth %
B18: 10-Year Charms | C18: 100 | D18: 0.08
B19: 15-Year Charms | C19: 40 | D19: 0.1
B20: Retail (Perpetual) Charms | C20: 15 | D20: 0.12
B22: UPSELL ATTACH RATES
B23: Extend Memory (monthly % of cumulative base) | C23: 0.02 | D23: Applied to cumulative charms sold
B24: Upgrade Tier (monthly % of cumulative base) | C24: 0.01
B25: Gift Wrap (% of new monthly charm sales) | C25: 0.15
B27: CONTENT SIZE ASSUMPTIONS | F27: API enforces 150 MB max per charm
B28: Media Type | C28: Avg Size (MB) | D28: % of Charms | E28: Weighted MB | F28: Weighted MB = Size x Mix %
B29: Video charms (single mp4/webm/mov) | C29: 55 | D29: 0.55 | E29: =C29*D29 -> 30.25 | F29: iPhone 1080p: HEVC ~20MB, H.264 ~65MB, 4K ~67MB for 30s
B30: Image gallery charms (1-20 images) | C30: 15 | D30: 0.35 | E30: =C30*D30 -> 5.25 | F30: ~4-6 iPhone photos avg at 2.5-4 MB each (HEIF/JPEG)
B31: Audio charms (single mp3/wav/ogg/aac) | C31: 6 | D31: 0.1 | E31: =C31*D31 -> 0.6 | F31: Voice message or song clip, 1-3 min
B32: Mix total (should = 100%) | D32: =D29+D30+D31 -> 1
B33: WEIGHTED AVG CONTENT SIZE (MB per charm) | C33: =E29+E30+E31 -> 36.1 | F33: Used for all storage cost calculations below
B34: Charm claim rate (% sold that get activated) | C34: 0.85 | F34: Unclaimed charms use zero storage
B35: Re-upload rate (% charms re-uploaded in 14-day settling) | C35: 0.2 | F35: Each re-upload = delete old + write new (extra ops)
B37: PLAYBACK & API REQUEST VOLUME
B38: Avg views per charm per month (first 3 months) | C38: 8 | F38: Novelty period — owner + shared views
B39: Avg views per charm per month (after 3 months) | C39: 2 | F39: Long-tail: occasional revisits
B40: % of views requiring glyph verification | C40: 0.4 | F40: Each glyph verify = 1 extra API call + Table write
B41: API CALLS PER CHARM LIFECYCLE (one-time) | C41: 5 | F41: claim + configure + get-upload-urls + finalize + owner-preview
B42: Table Storage writes per charm setup | C42: 8 | F42: charm entity + user-charm + profile + request log (sampled)
B43: Table Storage reads per charm view | C43: 3 | F43: GetCharm (entity lookup + rate-limit check + request log)
B45: AZURE BLOB STORAGE — COOL TIER (Backup) | F45: Azure is backup; R2 is primary CDN delivery
B46: Cost Component | C46: Rate | D46: Unit
B47: Storage (per GB per month) | C47: 0.01 | D47: $/GB/month | F47: Cool tier — $0.01/GB. Cold = $0.0036 (higher access)
B48: Write operations (per 10,000 ops) | C48: 0.1 | D48: $/10K writes | F48: PUT/Create blob — initial upload + re-uploads
B49: Read operations (per 10,000 ops) | C49: 0.01 | D49: $/10K reads | F49: GET blob — fallback downloads only (R2 is primary)
B50: Data retrieval (per GB downloaded) | C50: 0.01 | D50: $/GB retrieval | F50: Cool tier read penalty — only on Azure fallback reads
B51: Data egress (per GB, first 100 GB free/mo) | C51: 0.087 | D51: $/GB egress | F51: Only if client falls back from R2 — normally $0
B53: CLOUDFLARE R2 (Primary CDN — Zero Egress) | F53: S3-compatible; zero bandwidth/egress fees
B54: Cost Component | C54: Rate | D54: Unit
B55: Storage (per GB per month) | C55: 0.015 | D55: $/GB/month | F55: First 10 GB free; $0.015/GB after
B56: Class A ops — writes (per 1,000,000 ops) | C56: 4.5 | D56: $/1M Class A | F56: PUT/POST/LIST — uploads, re-uploads, finalize checks
B57: Class B ops — reads (per 1,000,000 ops) | C57: 0.36 | D57: $/1M Class B | F57: GET — every charm playback downloads from R2
B58: Egress (bandwidth) | C58: 0 | D58: $/GB | F58: ZERO — Cloudflare's key advantage
B59: R2 free tier (storage GB included free) | C59: 10 | D59: GB free/month | F59: Also: 10M Class A free, 10M Class B free per month
B61: AZURE TABLE STORAGE (Metadata & Telemetry)
B62: Cost Component | C62: Rate | D62: Unit
B63: Storage (per GB per month) | C63: 0.045 | D63: $/GB/month | F63: Charm entities, profiles, user-charms, request logs
B64: Transactions (per 10,000) | C64: 0.00036 | D64: $/10K txns | F64: Each read/write/query = 1 transaction
B65: Avg entity size (KB per charm record set) | C65: 2 | D65: KB | F65: charm + user-charm + profile share ≈ 2 KB total
B67: AZURE FUNCTIONS — CONSUMPTION PLAN
B68: Cost Component | C68: Rate | D68: Unit
B69: Executions (per 1,000,000) | C69: 0.2 | D69: $/1M executions | F69: First 1M/month FREE; then $0.20/million
B70: Compute (per GB-second) | C70: 1.6e-05 | D70: $/GB-s | F70: First 400K GB-s FREE; ~128MB × 200ms avg per call
B71: Avg execution duration (ms) | C71: 200 | D71: milliseconds | F71: Typical for table lookup + SAS URL generation
B72: Memory allocation (MB) | C72: 128 | D72: MB | F72: Consumption plan default; 128 MB minimum
B73: Free tier executions (per month) | C73: 1000000 | D73: executions
B74: Free tier GB-seconds (per month) | C74: 400000 | D74: GB-seconds
B76: OTHER PLATFORM COSTS (Monthly Fixed)
B77: Item | C77: Monthly Cost | D77: Notes
B78: Entra CIAM (Authentication) | C78: 0 | D78: Free: 50K MAU. $0.0025/MAU after that | F78: Per-MAU charge applies only beyond 50K monthly active users
B79: CIAM per-MAU cost (beyond 50K free) | C79: 0.0025 | D79: $/MAU above 50K
B80: Domain / SSL / DNS | C80: 15
B81: Application Insights / Monitoring | C81: 10 | D81: First 5 GB/mo free ingestion
B83: OPERATING EXPENSES (Monthly)
B84: Expense | C84: Monthly Cost | D84: MoM Growth %
B85: Marketing / Customer Acquisition | C85: 500 | D85: 0.05
B86: Shipping & Fulfillment (per charm shipped) | C86: 3.5 | D86: Per unit shipped
B87: Payment Processing (% of revenue) | C87: 0.029 | D87: Stripe / processor fee
B88: Customer Support | C88: 200 | D88: 0.03
B89: Insurance / Legal / Misc | C89: 150 | D89: 0
B91: OTHER ASSUMPTIONS
B92: Tax rate (on positive EBITDA) | C92: 0.21
B94: RETURNS & REPLACEMENTS | F94: Industry avg for specialty/gift items: 5-10% returns, 2-4% defects
B95: Item | C95: Rate / Cost | D95: Notes
B96: Return rate (% of monthly charm sales returned) | C96: 0.06 | D96: Specialty/gift items — lower than general e-commerce | F96: E-commerce avg ~15-30%; gift/keepsake items typically 5-8%
B97: % of returns that are pre-claim (restockable) | C97: 0.6 | D97: Charm bought but never claimed/configured | F97: Pre-claim charms can be wiped and resold; post-claim are dead stock
B98: Restocking salvage (% of COGS recovered on pre-claim returns) | C98: 0.8 | D98: Repackage & resell; some cosmetic loss | F98: Pre-claim charms only — post-claim have content, cannot resell
B99: Return shipping cost (company pays, per unit) | C99: 5 | F99: Return label cost; higher than outbound due to reverse logistics
B100: Return processing / handling cost (per unit) | C100: 2 | F100: Inspect, wipe NFC, repackage or dispose
B101: Replacement / defect rate (% of sales needing free replacement) | C101: 0.03 | D101: NFC failure, shipping damage, manufacturing defect | F101: Industry avg for electronics-adjacent: 2-5%
B102: Replacement shipping cost (per unit) | C102: 3.5 | F102: Same as outbound; may include expedited for goodwill
B103: Replacement COGS (% of original — may use cheaper housing) | C103: 1 | D103: 100% = full COGS; could be lower if reusing parts

Sheet 24-Month Projections
B1: MemoryCharm — 24-Month Financial Projections
B2: All values driven by Assumptions sheet — change inputs there
C4: Month 1 | D4: Month 2 | E4: Month 3 | F4: Month 4 | G4: Month 5 | H4: Month 6 | I4: Month 7 | J4: Month 8 | K4: Month 9 | L4: Month 10 | M4: Month 11 | N4: Month 12 | O4: Month 13 | P4: Month 14 | Q4: Month 15 | R4: Month 16 | S4: Month 17 | T4: Month 18 | U4: Month 19 | V4: Month 20 | W4: Month 21 | X4: Month 22 | Y4: Month 23 | Z4: Month 24
B5: UNIT SALES
B6: 10-Year Charms Sold | C6: =Assumptions!C18 -> 100 | D6: =ROUND(C6*(1+Assumptions!D18),0) -> 108 | E6: =ROUND(D6*(1+Assumptions!D18),0) -> 117 | F6: =ROUND(E6*(1+Assumptions!D18),0) -> 126 | G6: =ROUND(F6*(1+Assumptions!D18),0) -> 136 | H6: =ROUND(G6*(1+Assumptions!D18),0) -> 147 | I6: =ROUND(H6*(1+Assumptions!D18),0) -> 159 | J6: =ROUND(I6*(1+Assumptions!D18),0) -> 172 | K6: =ROUND(J6*(1+Assumptions!D18),0) -> 186 | L6: =ROUND(K6*(1+Assumptions!D18),0) -> 201 | M6: =ROUND(L6*(1+Assumptions!D18),0) -> 217 | N6: =ROUND(M6*(1+Assumptions!D18),0) -> 234 | O6: =ROUND(N6*(1+Assumptions!D18),0) -> 253 | P6: =ROUND(O6*(1+Assumptions!D18),0) -> 273 | Q6: =ROUND(P6*(1+Assumptions!D18),0) -> 295 | R6: =ROUND(Q6*(1+Assumptions!D18),0) -> 319 | S6: =ROUND(R6*(1+Assumptions!D18),0) -> 345 | T6: =ROUND(S6*(1+Assumptions!D18),0) -> 373 | U6: =ROUND(T6*(1+Assumptions!D18),0) -> 403 | V6: =ROUND(U6*(1+Assumptions!D18),0) -> 435 | W6: =ROUND(V6*(1+Assumptions!D18),0) -> 470 | X6: =ROUND(W6*(1+Assumptions!D18),0) -> 508 | Y6: =ROUND(X6*(1+Assumptions!D18),0) -> 549 | Z6: =ROUND(Y6*(1+Assumptions!D18),0) -> 593
B7: 15-Year Charms Sold | C7: =Assumptions!C19 -> 40 | D7: =ROUND(C7*(1+Assumptions!D19),0) -> 44 | E7: =ROUND(D7*(1+Assumptions!D19),0) -> 48 | F7: =ROUND(E7*(1+Assumptions!D19),0) -> 53 | G7: =ROUND(F7*(1+Assumptions!D19),0) -> 58 | H7: =ROUND(G7*(1+Assumptions!D19),0) -> 64 | I7: =ROUND(H7*(1+Assumptions!D19),0) -> 70 | J7: =ROUND(I7*(1+Assumptions!D19),0) -> 77 | K7: =ROUND(J7*(1+Assumptions!D19),0) -> 85 | L7: =ROUND(K7*(1+Assumptions!D19),0) -> 94 | M7: =ROUND(L7*(1+Assumptions!D19),0) -> 103 | N7: =ROUND(M7*(1+Assumptions!D19),0) -> 113 | O7: =ROUND(N7*(1+Assumptions!D19),0) -> 124 | P7: =ROUND(O7*(1+Assumptions!D19),0) -> 136 | Q7: =ROUND(P7*(1+Assumptions!D19),0) -> 150 | R7: =ROUND(Q7*(1+Assumptions!D19),0) -> 165 | S7: =ROUND(R7*(1+Assumptions!D19),0) -> 182 | T7: =ROUND(S7*(1+Assumptions!D19),0) -> 200 | U7: =ROUND(T7*(1+Assumptions!D19),0) -> 220 | V7: =ROUND(U7*(1+Assumptions!D19),0) -> 242 | W7: =ROUND(V7*(1+Assumptions!D19),0) -> 266 | X7: =ROUND(W7*(1+Assumptions!D19),0) -> 293 | Y7: =ROUND(X7*(1+Assumptions!D19),0) -> 322 | Z7: =ROUND(Y7*(1+Assumptions!D19),0) -> 354
B8: Retail (Perpetual) Charms Sold | C8: =Assumptions!C20 -> 15 | D8: =ROUND(C8*(1+Assumptions!D20),0) -> 17 | E8: =ROUND(D8*(1+Assumptions!D20),0) -> 19 | F8: =ROUND(E8*(1+Assumptions!D20),0) -> 21 | G8: =ROUND(F8*(1+Assumptions!D20),0) -> 24 | H8: =ROUND(G8*(1+Assumptions!D20),0) -> 27 | I8: =ROUND(H8*(1+Assumptions!D20),0) -> 30 | J8: =ROUND(I8*(1+Assumptions!D20),0) -> 34 | K8: =ROUND(J8*(1+Assumptions!D20),0) -> 38 | L8: =ROUND(K8*(1+Assumptions!D20),0) -> 43 | M8: =ROUND(L8*(1+Assumptions!D20),0) -> 48 | N8: =ROUND(M8*(1+Assumptions!D20),0) -> 54 | O8: =ROUND(N8*(1+Assumptions!D20),0) -> 60 | P8: =ROUND(O8*(1+Assumptions!D20),0) -> 67 | Q8: =ROUND(P8*(1+Assumptions!D20),0) -> 75 | R8: =ROUND(Q8*(1+Assumptions!D20),0) -> 84 | S8: =ROUND(R8*(1+Assumptions!D20),0) -> 94 | T8: =ROUND(S8*(1+Assumptions!D20),0) -> 105 | U8: =ROUND(T8*(1+Assumptions!D20),0) -> 118 | V8: =ROUND(U8*(1+Assumptions!D20),0) -> 132 | W8: =ROUND(V8*(1+Assumptions!D20),0) -> 148 | X8: =ROUND(W8*(1+Assumptions!D20),0) -> 166 | Y8: =ROUND(X8*(1+Assumptions!D20),0) -> 186 | Z8: =ROUND(Y8*(1+Assumptions!D20),0) -> 208
B9: Total Charms Sold (Month) | C9: =C6+C7+C8 -> 155 | D9: =D6+D7+D8 -> 169 | E9: =E6+E7+E8 -> 184 | F9: =F6+F7+F8 -> 200 | G9: =G6+G7+G8 -> 218 | H9: =H6+H7+H8 -> 238 | I9: =I6+I7+I8 -> 259 | J9: =J6+J7+J8 -> 283 | ... Z9: =Z6+Z7+Z8 -> 1155
B10: Cumulative Charms Sold | C10: =C9 -> 155 | D10: =C10+D9 -> 324 | E10: =D10+E9 -> 508 | F10: =E10+F9 -> 708 | G10: =F10+G9 -> 926 | H10: =G10+H9 -> 1164 | I10: =H10+I9 -> 1423 | J10: =I10+J9 -> 1706 | K10: =J10+K9 -> 2015 | ... Z10: =Y10+Z9 -> 12035
B11: Active Charms (claimed, storing content) | C11: =ROUND(C10*Assumptions!C34,0) -> 132 | D11: =ROUND(D10*Assumptions!C34,0) -> 275 | E11: =ROUND(E10*Assumptions!C34,0) -> 432 | F11: =ROUND(F10*Assumptions!C34,0) -> 602 | G11: =ROUND(G10*Assumptions!C34,0) -> 787 | H11: =ROUND(H10*Assumptions!C34,0) -> 989 | I11: =ROUND(I10*Assumptions!C34,0) -> 1210 | J11: =ROUND(J10*Assumptions!C34,0) -> 1450 | K11: =ROUND(K10*Assumptions!C34,0) -> 1713 | L11: =ROUND(L10*Assumptions!C34,0) -> 2000 | M11: =ROUND(M10*Assumptions!C34,0) -> 2313 | N11: =ROUND(N10*Assumptions!C34,0) -> 2654 | O11: =ROUND(O10*Assumptions!C34,0) -> 3025 | P11: =ROUND(P10*Assumptions!C34,0) -> 3430 | Q11: =ROUND(Q10*Assumptions!C34,0) -> 3872 | R11: =ROUND(R10*Assumptions!C34,0) -> 4355 | S11: =ROUND(S10*Assumptions!C34,0) -> 4882 | T11: =ROUND(T10*Assumptions!C34,0) -> 5459 | U11: =ROUND(U10*Assumptions!C34,0) -> 6089 | V11: =ROUND(V10*Assumptions!C34,0) -> 6776 | W11: =ROUND(W10*Assumptions!C34,0) -> 7528 | X11: =ROUND(X10*Assumptions!C34,0) -> 8350 | Y11: =ROUND(Y10*Assumptions!C34,0) -> 9248 | Z11: =ROUND(Z10*Assumptions!C34,0) -> 10230
B13: STORAGE VOLUME
B14: New Content Uploaded (GB) | C14: =ROUND(C9*Assumptions!C34*Assumptions!C33/1024,2) -> 4.64 | D14: =ROUND(D9*Assumptions!C34*Assumptions!C33/1024,2) -> 5.06 | E14: =ROUND(E9*Assumptions!C34*Assumptions!C33/1024,2) -> 5.51 | F14: =ROUND(F9*Assumptions!C34*Assumptions!C33/1024,2) -> 5.99 | G14: =ROUND(G9*Assumptions!C34*Assumptions!C33/1024,2) -> 6.53 | H14: =ROUND(H9*Assumptions!C34*Assumptions!C33/1024,2) -> 7.13 | I14: =ROUND(I9*Assumptions!C34*Assumptions!C33/1024,2) -> 7.76 | J14: =ROUND(J9*Assumptions!C34*Assumptions!C33/1024,2) -> 8.48 | K14: =ROUND(K9*Assumptions!C34*Assumptions!C33/1024,2) -> 9.26 | L14: =ROUND(L9*Assumptions!C34*Assumptions!C33/1024,2) -> 10.13 | M14: =ROUND(M9*Assumptions!C34*Assumptions!C33/1024,2) -> 11.03 | N14: =ROUND(N9*Assumptions!C34*Assumptions!C33/1024,2) -> 12.02 | O14: =ROUND(O9*Assumptions!C34*Assumptions!C33/1024,2) -> 13.1 | P14: =ROUND(P9*Assumptions!C34*Assumptions!C33/1024,2) -> 14.26 | Q14: =ROUND(Q9*Assumptions!C34*Assumptions!C33/1024,2) -> 15.58 | R14: =ROUND(R9*Assumptions!C34*Assumptions!C33/1024,2) -> 17.02 | S14: =ROUND(S9*Assumptions!C34*Assumptions!C33/1024,2) -> 18.61 | T14: =ROUND(T9*Assumptions!C34*Assumptions!C33/1024,2) -> 20.32 | U14: =ROUND(U9*Assumptions!C34*Assumptions!C33/1024,2) -> 22.2 | V14: =ROUND(V9*Assumptions!C34*Assumptions!C33/1024,2) -> 24.24 | W14: =ROUND(W9*Assumptions!C34*Assumptions!C33/1024,2) -> 26.49 | X14: =ROUND(X9*Assumptions!C34*Assumptions!C33/1024,2) -> 28.98 | Y14: =ROUND(Y9*Assumptions!C34*Assumptions!C33/1024,2) -> 31.67 | Z14: =ROUND(Z9*Assumptions!C34*Assumptions!C33/1024,2) -> 34.61
B15: Cumulative Content Stored (GB) | C15: =C14 -> 4.64 | D15: =C15+D14 -> 9.7 | E15: =D15+E14 -> 15.21 | F15: =E15+F14 -> 21.2 | G15: =F15+G14 -> 27.73 | H15: =G15+H14 -> 34.86 | I15: =H15+I14 -> 42.62 | J15: =I15+J14 -> 51.1 | K15: =J15+K14 -> 60.36 | ... Z15: =Y15+Z14 -> 360.62
B16: Cloudflare R2 Storage (GB) | C16: =C15 -> 4.64 | D16: =D15 -> 9.7 | E16: =E15 -> 15.21 | F16: =F15 -> 21.2 | G16: =G15 -> 27.73 | H16: =H15 -> 34.86 | I16: =I15 -> 42.62 | J16: =J15 -> 51.1 | ... Z16: =Z15 -> 360.62
B17: Azure Blob Cool Storage (GB) | C17: =C15 -> 4.64 | D17: =D15 -> 9.7 | E17: =E15 -> 15.21 | F17: =F15 -> 21.2 | G17: =G15 -> 27.73 | H17: =H15 -> 34.86 | I17: =I15 -> 42.62 | J17: =J15 -> 51.1 | ... Z17: =Z15 -> 360.62
B19: API & STORAGE REQUEST VOLUME
B20: Total Charm Playback Views (month) | C20: =ROUND(C9*Assumptions!C38+MAX(0,C11-C9)*Assumptions!C39,0) -> 1240 | D20: =ROUND((D9+C9)*Assumptions!C38+MAX(0,D11-(D9+C9))*Assumptions!C39,0) -> 2592 | E20: =ROUND((E9+D9+C9)*Assumptions!C38+MAX(0,E11-(E9+D9+C9))*Assumptions!C39,0) -> 4064 | F20: =ROUND((F9+E9+D9)*Assumptions!C38+MAX(0,F11-(F9+E9+D9))*Assumptions!C39,0) -> 4522 | G20: =ROUND((G9+F9+E9)*Assumptions!C38+MAX(0,G11-(G9+F9+E9))*Assumptions!C39,0) -> 5186 | H20: =ROUND((H9+G9+F9)*Assumptions!C38+MAX(0,H11-(H9+G9+F9))*Assumptions!C39,0) -> 5914 | I20: =ROUND((I9+H9+G9)*Assumptions!C38+MAX(0,I11-(I9+H9+G9))*Assumptions!C39,0) -> 6710 | J20: =ROUND((J9+I9+H9)*Assumptions!C38+MAX(0,J11-(J9+I9+H9))*Assumptions!C39,0) -> 7580 | K20: =ROUND((K9+J9+I9)*Assumptions!C38+MAX(0,K11-(K9+J9+I9))*Assumptions!C39,0) -> 8532 | L20: =ROUND((L9+K9+J9)*Assumptions!C38+MAX(0,L11-(L9+K9+J9))*Assumptions!C39,0) -> 9580 | M20: =ROUND((M9+L9+K9)*Assumptions!C38+MAX(0,M11-(M9+L9+K9))*Assumptions!C39,0) -> 10716 | N20: =ROUND((N9+M9+L9)*Assumptions!C38+MAX(0,N11-(N9+M9+L9))*Assumptions!C39,0) -> 11950 | O20: =ROUND((O9+N9+M9)*Assumptions!C38+MAX(0,O11-(O9+N9+M9))*Assumptions!C39,0) -> 13286 | P20: =ROUND((P9+O9+N9)*Assumptions!C38+MAX(0,P11-(P9+O9+N9))*Assumptions!C39,0) -> 14744 | Q20: =ROUND((Q9+P9+O9)*Assumptions!C38+MAX(0,Q11-(Q9+P9+O9))*Assumptions!C39,0) -> 16342 | R20: =ROUND((R9+Q9+P9)*Assumptions!C38+MAX(0,R11-(R9+Q9+P9))*Assumptions!C39,0) -> 18094 | S20: =ROUND((S9+R9+Q9)*Assumptions!C38+MAX(0,S11-(S9+R9+Q9))*Assumptions!C39,0) -> 20018 | T20: =ROUND((T9+S9+R9)*Assumptions!C38+MAX(0,T11-(T9+S9+R9))*Assumptions!C39,0) -> 22120 | U20: =ROUND((U9+T9+S9)*Assumptions!C38+MAX(0,U11-(U9+T9+S9))*Assumptions!C39,0) -> 24418 | V20: =ROUND((V9+U9+T9)*Assumptions!C38+MAX(0,V11-(V9+U9+T9))*Assumptions!C39,0) -> 26920 | W20: =ROUND((W9+V9+U9)*Assumptions!C38+MAX(0,W11-(W9+V9+U9))*Assumptions!C39,0) -> 29660 | X20: =ROUND((X9+W9+V9)*Assumptions!C38+MAX(0,X11-(X9+W9+V9))*Assumptions!C39,0) -> 32660 | Y20: =ROUND((Y9+X9+W9)*Assumptions!C38+MAX(0,Y11-(Y9+X9+W9))*Assumptions!C39,0) -> 35944 | Z20: =ROUND((Z9+Y9+X9)*Assumptions!C38+MAX(0,Z11-(Z9+Y9+X9))*Assumptions!C39,0) -> 39534
B21: Glyph Verification API Calls | C21: =ROUND(C20*Assumptions!C40,0) -> 496 | D21: =ROUND(D20*Assumptions!C40,0) -> 1037 | E21: =ROUND(E20*Assumptions!C40,0) -> 1626 | F21: =ROUND(F20*Assumptions!C40,0) -> 1809 | G21: =ROUND(G20*Assumptions!C40,0) -> 2074 | H21: =ROUND(H20*Assumptions!C40,0) -> 2366 | I21: =ROUND(I20*Assumptions!C40,0) -> 2684 | J21: =ROUND(J20*Assumptions!C40,0) -> 3032 | K21: =ROUND(K20*Assumptions!C40,0) -> 3413 | L21: =ROUND(L20*Assumptions!C40,0) -> 3832 | M21: =ROUND(M20*Assumptions!C40,0) -> 4286 | N21: =ROUND(N20*Assumptions!C40,0) -> 4780 | O21: =ROUND(O20*Assumptions!C40,0) -> 5314 | P21: =ROUND(P20*Assumptions!C40,0) -> 5898 | Q21: =ROUND(Q20*Assumptions!C40,0) -> 6537 | R21: =ROUND(R20*Assumptions!C40,0) -> 7238 | S21: =ROUND(S20*Assumptions!C40,0) -> 8007 | T21: =ROUND(T20*Assumptions!C40,0) -> 8848 | U21: =ROUND(U20*Assumptions!C40,0) -> 9767 | V21: =ROUND(V20*Assumptions!C40,0) -> 10768 | W21: =ROUND(W20*Assumptions!C40,0) -> 11864 | X21: =ROUND(X20*Assumptions!C40,0) -> 13064 | Y21: =ROUND(Y20*Assumptions!C40,0) -> 14378 | Z21: =ROUND(Z20*Assumptions!C40,0) -> 15814
B22: Total Azure Functions Invocations | C22: =ROUND((C9*Assumptions!C34*Assumptions!C41)+C20+C21+(C20*0.02),0) -> 2420 | D22: =ROUND((D9*Assumptions!C34*Assumptions!C41)+D20+D21+(D20*0.02),0) -> 4399 | E22: =ROUND((E9*Assumptions!C34*Assumptions!C41)+E20+E21+(E20*0.02),0) -> 6553 | F22: =ROUND((F9*Assumptions!C34*Assumptions!C41)+F20+F21+(F20*0.02),0) -> 7271 | G22: =ROUND((G9*Assumptions!C34*Assumptions!C41)+G20+G21+(G20*0.02),0) -> 8290 | H22: =ROUND((H9*Assumptions!C34*Assumptions!C41)+H20+H21+(H20*0.02),0) -> 9410 | I22: =ROUND((I9*Assumptions!C34*Assumptions!C41)+I20+I21+(I20*0.02),0) -> 10629 | J22: =ROUND((J9*Assumptions!C34*Assumptions!C41)+J20+J21+(J20*0.02),0) -> 11966 | K22: =ROUND((K9*Assumptions!C34*Assumptions!C41)+K20+K21+(K20*0.02),0) -> 13429 | L22: =ROUND((L9*Assumptions!C34*Assumptions!C41)+L20+L21+(L20*0.02),0) -> 15040 | M22: =ROUND((M9*Assumptions!C34*Assumptions!C41)+M20+M21+(M20*0.02),0) -> 16780 | N22: =ROUND((N9*Assumptions!C34*Assumptions!C41)+N20+N21+(N20*0.02),0) -> 18673 | O22: =ROUND((O9*Assumptions!C34*Assumptions!C41)+O20+O21+(O20*0.02),0) -> 20723 | P22: =ROUND((P9*Assumptions!C34*Assumptions!C41)+P20+P21+(P20*0.02),0) -> 22960 | Q22: =ROUND((Q9*Assumptions!C34*Assumptions!C41)+Q20+Q21+(Q20*0.02),0) -> 25416 | R22: =ROUND((R9*Assumptions!C34*Assumptions!C41)+R20+R21+(R20*0.02),0) -> 28108 | S22: =ROUND((S9*Assumptions!C34*Assumptions!C41)+S20+S21+(S20*0.02),0) -> 31065 | T22: =ROUND((T9*Assumptions!C34*Assumptions!C41)+T20+T21+(T20*0.02),0) -> 34292 | U22: =ROUND((U9*Assumptions!C34*Assumptions!C41)+U20+U21+(U20*0.02),0) -> 37823 | V22: =ROUND((V9*Assumptions!C34*Assumptions!C41)+V20+V21+(V20*0.02),0) -> 41665 | W22: =ROUND((W9*Assumptions!C34*Assumptions!C41)+W20+W21+(W20*0.02),0) -> 45874 | X22: =ROUND((X9*Assumptions!C34*Assumptions!C41)+X20+X21+(X20*0.02),0) -> 50487 | Y22: =ROUND((Y9*Assumptions!C34*Assumptions!C41)+Y20+Y21+(Y20*0.02),0) -> 55533 | Z22: =ROUND((Z9*Assumptions!C34*Assumptions!C41)+Z20+Z21+(Z20*0.02),0) -> 61047
B23: R2 Class A Ops (Writes) | C23: =ROUND(C9*Assumptions!C34*2*(1+Assumptions!C35),0) -> 316 | D23: =ROUND(D9*Assumptions!C34*2*(1+Assumptions!C35),0) -> 345 | E23: =ROUND(E9*Assumptions!C34*2*(1+Assumptions!C35),0) -> 375 | F23: =ROUND(F9*Assumptions!C34*2*(1+Assumptions!C35),0) -> 408 | G23: =ROUND(G9*Assumptions!C34*2*(1+Assumptions!C35),0) -> 445 | H23: =ROUND(H9*Assumptions!C34*2*(1+Assumptions!C35),0) -> 486 | I23: =ROUND(I9*Assumptions!C34*2*(1+Assumptions!C35),0) -> 528 | J23: =ROUND(J9*Assumptions!C34*2*(1+Assumptions!C35),0) -> 577 | K23: =ROUND(K9*Assumptions!C34*2*(1+Assumptions!C35),0) -> 630 | L23: =ROUND(L9*Assumptions!C34*2*(1+Assumptions!C35),0) -> 690 | M23: =ROUND(M9*Assumptions!C34*2*(1+Assumptions!C35),0) -> 751 | N23: =ROUND(N9*Assumptions!C34*2*(1+Assumptions!C35),0) -> 818 | O23: =ROUND(O9*Assumptions!C34*2*(1+Assumptions!C35),0) -> 891 | P23: =ROUND(P9*Assumptions!C34*2*(1+Assumptions!C35),0) -> 971 | Q23: =ROUND(Q9*Assumptions!C34*2*(1+Assumptions!C35),0) -> 1061 | R23: =ROUND(R9*Assumptions!C34*2*(1+Assumptions!C35),0) -> 1159 | S23: =ROUND(S9*Assumptions!C34*2*(1+Assumptions!C35),0) -> 1267 | T23: =ROUND(T9*Assumptions!C34*2*(1+Assumptions!C35),0) -> 1383 | U23: =ROUND(U9*Assumptions!C34*2*(1+Assumptions!C35),0) -> 1512 | V23: =ROUND(V9*Assumptions!C34*2*(1+Assumptions!C35),0) -> 1650 | W23: =ROUND(W9*Assumptions!C34*2*(1+Assumptions!C35),0) -> 1803 | X23: =ROUND(X9*Assumptions!C34*2*(1+Assumptions!C35),0) -> 1973 | Y23: =ROUND(Y9*Assumptions!C34*2*(1+Assumptions!C35),0) -> 2156 | Z23: =ROUND(Z9*Assumptions!C34*2*(1+Assumptions!C35),0) -> 2356
B24: R2 Class B Ops (Reads / Playback) | C24: =C20 -> 1240 | D24: =D20 -> 2592 | E24: =E20 -> 4064 | F24: =F20 -> 4522 | G24: =G20 -> 5186 | H24: =H20 -> 5914 | I24: =I20 -> 6710 | J24: =J20 -> 7580 | ... Z24: =Z20 -> 39534
B25: Azure Blob Write Ops (Backup Uploads) | C25: =C23 -> 316 | D25: =D23 -> 345 | E25: =E23 -> 375 | F25: =F23 -> 408 | G25: =G23 -> 445 | H25: =H23 -> 486 | I25: =I23 -> 528 | J25: =J23 -> 577 | ... Z25: =Z23 -> 2356
B26: Azure Blob Read Ops (Fallback — est 2%) | C26: =ROUND(C20*0.02,0) -> 25 | D26: =ROUND(D20*0.02,0) -> 52 | E26: =ROUND(E20*0.02,0) -> 81 | F26: =ROUND(F20*0.02,0) -> 90 | G26: =ROUND(G20*0.02,0) -> 104 | H26: =ROUND(H20*0.02,0) -> 118 | I26: =ROUND(I20*0.02,0) -> 134 | J26: =ROUND(J20*0.02,0) -> 152 | ... Z26: =ROUND(Z20*0.02,0) -> 791
B27: Azure Table Transactions (Total) | C27: =ROUND(C9*Assumptions!C34*Assumptions!C42+C20*Assumptions!C43+C21*2,0) -> 5766 | D27: =ROUND(D9*Assumptions!C34*Assumptions!C42+D20*Assumptions!C43+D21*2,0) -> 10999 | E27: =ROUND(E9*Assumptions!C34*Assumptions!C42+E20*Assumptions!C43+E21*2,0) -> 16695 | F27: =ROUND(F9*Assumptions!C34*Assumptions!C42+F20*Assumptions!C43+F21*2,0) -> 18544 | G27: =ROUND(G9*Assumptions!C34*Assumptions!C42+G20*Assumptions!C43+G21*2,0) -> 21188 | H27: =ROUND(H9*Assumptions!C34*Assumptions!C42+H20*Assumptions!C43+H21*2,0) -> 24092 | I27: =ROUND(I9*Assumptions!C34*Assumptions!C42+I20*Assumptions!C43+I21*2,0) -> 27259 | J27: =ROUND(J9*Assumptions!C34*Assumptions!C42+J20*Assumptions!C43+J21*2,0) -> 30728 | K27: =ROUND(K9*Assumptions!C34*Assumptions!C42+K20*Assumptions!C43+K21*2,0) -> 34523 | L27: =ROUND(L9*Assumptions!C34*Assumptions!C42+L20*Assumptions!C43+L21*2,0) -> 38702 | M27: =ROUND(M9*Assumptions!C34*Assumptions!C42+M20*Assumptions!C43+M21*2,0) -> 43222 | N27: =ROUND(N9*Assumptions!C34*Assumptions!C42+N20*Assumptions!C43+N21*2,0) -> 48137 | O27: =ROUND(O9*Assumptions!C34*Assumptions!C42+O20*Assumptions!C43+O21*2,0) -> 53458 | P27: =ROUND(P9*Assumptions!C34*Assumptions!C42+P20*Assumptions!C43+P21*2,0) -> 59265 | Q27: =ROUND(Q9*Assumptions!C34*Assumptions!C42+Q20*Assumptions!C43+Q21*2,0) -> 65636 | R27: =ROUND(R9*Assumptions!C34*Assumptions!C42+R20*Assumptions!C43+R21*2,0) -> 72620 | S27: =ROUND(S9*Assumptions!C34*Assumptions!C42+S20*Assumptions!C43+S21*2,0) -> 80291 | T27: =ROUND(T9*Assumptions!C34*Assumptions!C42+T20*Assumptions!C43+T21*2,0) -> 88666 | U27: =ROUND(U9*Assumptions!C34*Assumptions!C42+U20*Assumptions!C43+U21*2,0) -> 97827 | V27: =ROUND(V9*Assumptions!C34*Assumptions!C42+V20*Assumptions!C43+V21*2,0) -> 107797 | W27: =ROUND(W9*Assumptions!C34*Assumptions!C42+W20*Assumptions!C43+W21*2,0) -> 118719 | X27: =ROUND(X9*Assumptions!C34*Assumptions!C42+X20*Assumptions!C43+X21*2,0) -> 130684 | Y27: =ROUND(Y9*Assumptions!C34*Assumptions!C42+Y20*Assumptions!C43+Y21*2,0) -> 143776 | Z27: =ROUND(Z9*Assumptions!C34*Assumptions!C42+Z20*Assumptions!C43+Z21*2,0) -> 158084
B28: R2 Playback Bandwidth (GB) — FREE egress | C28: =ROUND(C20*Assumptions!C33/1024,1) -> 43.7 | D28: =ROUND(D20*Assumptions!C33/1024,1) -> 91.4 | E28: =ROUND(E20*Assumptions!C33/1024,1) -> 143.3 | F28: =ROUND(F20*Assumptions!C33/1024,1) -> 159.4 | G28: =ROUND(G20*Assumptions!C33/1024,1) -> 182.8 | H28: =ROUND(H20*Assumptions!C33/1024,1) -> 208.5 | I28: =ROUND(I20*Assumptions!C33/1024,1) -> 236.6 | J28: =ROUND(J20*Assumptions!C33/1024,1) -> 267.2 | K28: =ROUND(K20*Assumptions!C33/1024,1) -> 300.8 | L28: =ROUND(L20*Assumptions!C33/1024,1) -> 337.7 | M28: =ROUND(M20*Assumptions!C33/1024,1) -> 377.8 | N28: =ROUND(N20*Assumptions!C33/1024,1) -> 421.3 | O28: =ROUND(O20*Assumptions!C33/1024,1) -> 468.4 | P28: =ROUND(P20*Assumptions!C33/1024,1) -> 519.8 | Q28: =ROUND(Q20*Assumptions!C33/1024,1) -> 576.1 | R28: =ROUND(R20*Assumptions!C33/1024,1) -> 637.9 | S28: =ROUND(S20*Assumptions!C33/1024,1) -> 705.7 | T28: =ROUND(T20*Assumptions!C33/1024,1) -> 779.8 | U28: =ROUND(U20*Assumptions!C33/1024,1) -> 860.8 | V28: =ROUND(V20*Assumptions!C33/1024,1) -> 949 | W28: =ROUND(W20*Assumptions!C33/1024,1) -> 1045.6 | X28: =ROUND(X20*Assumptions!C33/1024,1) -> 1151.4 | Y28: =ROUND(Y20*Assumptions!C33/1024,1) -> 1267.2 | Z28: =ROUND(Z20*Assumptions!C33/1024,1) -> 1393.7
B30: INFRASTRUCTURE COST BREAKDOWN
B31: Azure Blob: Storage Cost | C31: =C17*Assumptions!C47 -> 0.0464 | D31: =D17*Assumptions!C47 -> 0.097 | E31: =E17*Assumptions!C47 -> 0.1521 | F31: =F17*Assumptions!C47 -> 0.212 | G31: =G17*Assumptions!C47 -> 0.2773 | H31: =H17*Assumptions!C47 -> 0.3486 | I31: =I17*Assumptions!C47 -> 0.4262 | J31: =J17*Assumptions!C47 -> 0.511 | K31: =K17*Assumptions!C47 -> 0.6036 | L31: =L17*Assumptions!C47 -> 0.7049 | M31: =M17*Assumptions!C47 -> 0.8152 | N31: =N17*Assumptions!C47 -> 0.9354 | O31: =O17*Assumptions!C47 -> 1.0664 | P31: =P17*Assumptions!C47 -> 1.209 | Q31: =Q17*Assumptions!C47 -> 1.3648 | R31: =R17*Assumptions!C47 -> 1.535 | S31: =S17*Assumptions!C47 -> 1.7211 | T31: =T17*Assumptions!C47 -> 1.9243 | U31: =U17*Assumptions!C47 -> 2.1463 | V31: =V17*Assumptions!C47 -> 2.3887 | W31: =W17*Assumptions!C47 -> 2.6536 | X31: =X17*Assumptions!C47 -> 2.9434 | Y31: =Y17*Assumptions!C47 -> 3.2601 | Z31: =Z17*Assumptions!C47 -> 3.6062
B32: Azure Blob: Write Operations | C32: =(C25/10000)*Assumptions!C48 -> 0.00316 | D32: =(D25/10000)*Assumptions!C48 -> 0.00345 | E32: =(E25/10000)*Assumptions!C48 -> 0.00375 | F32: =(F25/10000)*Assumptions!C48 -> 0.00408 | G32: =(G25/10000)*Assumptions!C48 -> 0.00445 | H32: =(H25/10000)*Assumptions!C48 -> 0.00486 | I32: =(I25/10000)*Assumptions!C48 -> 0.00528 | J32: =(J25/10000)*Assumptions!C48 -> 0.00577 | K32: =(K25/10000)*Assumptions!C48 -> 0.0063 | L32: =(L25/10000)*Assumptions!C48 -> 0.0069 | M32: =(M25/10000)*Assumptions!C48 -> 0.00751 | N32: =(N25/10000)*Assumptions!C48 -> 0.00818 | O32: =(O25/10000)*Assumptions!C48 -> 0.00891 | P32: =(P25/10000)*Assumptions!C48 -> 0.00971 | Q32: =(Q25/10000)*Assumptions!C48 -> 0.01061 | R32: =(R25/10000)*Assumptions!C48 -> 0.01159 | S32: =(S25/10000)*Assumptions!C48 -> 0.01267 | T32: =(T25/10000)*Assumptions!C48 -> 0.01383 | U32: =(U25/10000)*Assumptions!C48 -> 0.01512 | V32: =(V25/10000)*Assumptions!C48 -> 0.0165 | W32: =(W25/10000)*Assumptions!C48 -> 0.01803 | X32: =(X25/10000)*Assumptions!C48 -> 0.01973 | Y32: =(Y25/10000)*Assumptions!C48 -> 0.02156 | Z32: =(Z25/10000)*Assumptions!C48 -> 0.02356
B33: Azure Blob: Read Ops (Fallback) | C33: =(C26/10000)*Assumptions!C49 -> 2.5e-05 | D33: =(D26/10000)*Assumptions!C49 -> 5.2e-05 | E33: =(E26/10000)*Assumptions!C49 -> 8.1e-05 | F33: =(F26/10000)*Assumptions!C49 -> 9e-05 | G33: =(G26/10000)*Assumptions!C49 -> 0.000104 | H33: =(H26/10000)*Assumptions!C49 -> 0.000118 | I33: =(I26/10000)*Assumptions!C49 -> 0.000134 | J33: =(J26/10000)*Assumptions!C49 -> 0.000152 | K33: =(K26/10000)*Assumptions!C49 -> 0.000171 | L33: =(L26/10000)*Assumptions!C49 -> 0.000192 | M33: =(M26/10000)*Assumptions!C49 -> 0.000214 | N33: =(N26/10000)*Assumptions!C49 -> 0.000239 | O33: =(O26/10000)*Assumptions!C49 -> 0.000266 | P33: =(P26/10000)*Assumptions!C49 -> 0.000295 | Q33: =(Q26/10000)*Assumptions!C49 -> 0.000327 | R33: =(R26/10000)*Assumptions!C49 -> 0.000362 | S33: =(S26/10000)*Assumptions!C49 -> 0.0004 | T33: =(T26/10000)*Assumptions!C49 -> 0.000442 | U33: =(U26/10000)*Assumptions!C49 -> 0.000488 | V33: =(V26/10000)*Assumptions!C49 -> 0.000538 | W33: =(W26/10000)*Assumptions!C49 -> 0.000593 | X33: =(X26/10000)*Assumptions!C49 -> 0.000653 | Y33: =(Y26/10000)*Assumptions!C49 -> 0.000719 | Z33: =(Z26/10000)*Assumptions!C49 -> 0.000791
B34: Azure Blob: Data Retrieval (Fallback) | C34: =(C26*Assumptions!C33/1024)*Assumptions!C50 -> 0.0088134766 | D34: =(D26*Assumptions!C33/1024)*Assumptions!C50 -> 0.018332031 | E34: =(E26*Assumptions!C33/1024)*Assumptions!C50 -> 0.028555664 | F34: =(F26*Assumptions!C33/1024)*Assumptions!C50 -> 0.031728516 | G34: =(G26*Assumptions!C33/1024)*Assumptions!C50 -> 0.036664063 | H34: =(H26*Assumptions!C33/1024)*Assumptions!C50 -> 0.041599609 | I34: =(I26*Assumptions!C33/1024)*Assumptions!C50 -> 0.047240234 | J34: =(J26*Assumptions!C33/1024)*Assumptions!C50 -> 0.053585937 | K34: =(K26*Assumptions!C33/1024)*Assumptions!C50 -> 0.06028418 | L34: =(L26*Assumptions!C33/1024)*Assumptions!C50 -> 0.0676875 | M34: =(M26*Assumptions!C33/1024)*Assumptions!C50 -> 0.075443359 | N34: =(N26*Assumptions!C33/1024)*Assumptions!C50 -> 0.084256836 | O34: =(O26*Assumptions!C33/1024)*Assumptions!C50 -> 0.093775391 | P34: =(P26*Assumptions!C33/1024)*Assumptions!C50 -> 0.10399902 | Q34: =(Q26*Assumptions!C33/1024)*Assumptions!C50 -> 0.11528027 | R34: =(R26*Assumptions!C33/1024)*Assumptions!C50 -> 0.12761914 | S34: =(S26*Assumptions!C33/1024)*Assumptions!C50 -> 0.14101563 | T34: =(T26*Assumptions!C33/1024)*Assumptions!C50 -> 0.15582227 | U34: =(U26*Assumptions!C33/1024)*Assumptions!C50 -> 0.17203906 | V34: =(V26*Assumptions!C33/1024)*Assumptions!C50 -> 0.18966602 | W34: =(W26*Assumptions!C33/1024)*Assumptions!C50 -> 0.20905566 | X34: =(X26*Assumptions!C33/1024)*Assumptions!C50 -> 0.23020801 | Y34: =(Y26*Assumptions!C33/1024)*Assumptions!C50 -> 0.25347559 | Z34: =(Z26*Assumptions!C33/1024)*Assumptions!C50 -> 0.2788584
B35: Azure Blob Total | C35: =C31+C32+C33+C34 -> 0.058398477 | D35: =D31+D32+D33+D34 -> 0.11883403 | E35: =E31+E32+E33+E34 -> 0.18448666 | F35: =F31+F32+F33+F34 -> 0.24789852 | G35: =G31+G32+G33+G34 -> 0.31851806 | H35: =H31+H32+H33+H34 -> 0.39517761 | I35: =I31+I32+I33+I34 -> 0.47885423 | J35: =J31+J32+J33+J34 -> 0.57050794 | ... Z35: =Z31+Z32+Z33+Z34 -> 3.9094094
B36: R2: Storage Cost | C36: =MAX(0,C16-Assumptions!C59)*Assumptions!C55 -> 0 | D36: =MAX(0,D16-Assumptions!C59)*Assumptions!C55 -> 0 | E36: =MAX(0,E16-Assumptions!C59)*Assumptions!C55 -> 0.07815 | F36: =MAX(0,F16-Assumptions!C59)*Assumptions!C55 -> 0.168 | G36: =MAX(0,G16-Assumptions!C59)*Assumptions!C55 -> 0.26595 | H36: =MAX(0,H16-Assumptions!C59)*Assumptions!C55 -> 0.3729 | I36: =MAX(0,I16-Assumptions!C59)*Assumptions!C55 -> 0.4893 | J36: =MAX(0,J16-Assumptions!C59)*Assumptions!C55 -> 0.6165 | K36: =MAX(0,K16-Assumptions!C59)*Assumptions!C55 -> 0.7554 | L36: =MAX(0,L16-Assumptions!C59)*Assumptions!C55 -> 0.90735 | M36: =MAX(0,M16-Assumptions!C59)*Assumptions!C55 -> 1.0728 | N36: =MAX(0,N16-Assumptions!C59)*Assumptions!C55 -> 1.2531 | O36: =MAX(0,O16-Assumptions!C59)*Assumptions!C55 -> 1.4496 | P36: =MAX(0,P16-Assumptions!C59)*Assumptions!C55 -> 1.6635 | Q36: =MAX(0,Q16-Assumptions!C59)*Assumptions!C55 -> 1.8972 | R36: =MAX(0,R16-Assumptions!C59)*Assumptions!C55 -> 2.1525 | S36: =MAX(0,S16-Assumptions!C59)*Assumptions!C55 -> 2.43165 | T36: =MAX(0,T16-Assumptions!C59)*Assumptions!C55 -> 2.73645 | U36: =MAX(0,U16-Assumptions!C59)*Assumptions!C55 -> 3.06945 | V36: =MAX(0,V16-Assumptions!C59)*Assumptions!C55 -> 3.43305 | W36: =MAX(0,W16-Assumptions!C59)*Assumptions!C55 -> 3.8304 | X36: =MAX(0,X16-Assumptions!C59)*Assumptions!C55 -> 4.2651 | Y36: =MAX(0,Y16-Assumptions!C59)*Assumptions!C55 -> 4.74015 | Z36: =MAX(0,Z16-Assumptions!C59)*Assumptions!C55 -> 5.2593
B37: R2: Class A Ops (Writes) | C37: =MAX(0,C23-10000000)*Assumptions!C56/1000000 -> 0 | D37: =MAX(0,D23-10000000)*Assumptions!C56/1000000 -> 0 | E37: =MAX(0,E23-10000000)*Assumptions!C56/1000000 -> 0 | F37: =MAX(0,F23-10000000)*Assumptions!C56/1000000 -> 0 | G37: =MAX(0,G23-10000000)*Assumptions!C56/1000000 -> 0 | H37: =MAX(0,H23-10000000)*Assumptions!C56/1000000 -> 0 | I37: =MAX(0,I23-10000000)*Assumptions!C56/1000000 -> 0 | J37: =MAX(0,J23-10000000)*Assumptions!C56/1000000 -> 0 | K37: =MAX(0,K23-10000000)*Assumptions!C56/1000000 -> 0 | L37: =MAX(0,L23-10000000)*Assumptions!C56/1000000 -> 0 | M37: =MAX(0,M23-10000000)*Assumptions!C56/1000000 -> 0 | N37: =MAX(0,N23-10000000)*Assumptions!C56/1000000 -> 0 | O37: =MAX(0,O23-10000000)*Assumptions!C56/1000000 -> 0 | P37: =MAX(0,P23-10000000)*Assumptions!C56/1000000 -> 0 | Q37: =MAX(0,Q23-10000000)*Assumptions!C56/1000000 -> 0 | R37: =MAX(0,R23-10000000)*Assumptions!C56/1000000 -> 0 | S37: =MAX(0,S23-10000000)*Assumptions!C56/1000000 -> 0 | T37: =MAX(0,T23-10000000)*Assumptions!C56/1000000 -> 0 | U37: =MAX(0,U23-10000000)*Assumptions!C56/1000000 -> 0 | V37: =MAX(0,V23-10000000)*Assumptions!C56/1000000 -> 0 | W37: =MAX(0,W23-10000000)*Assumptions!C56/1000000 -> 0 | X37: =MAX(0,X23-10000000)*Assumptions!C56/1000000 -> 0 | Y37: =MAX(0,Y23-10000000)*Assumptions!C56/1000000 -> 0 | Z37: =MAX(0,Z23-10000000)*Assumptions!C56/1000000 -> 0
B38: R2: Class B Ops (Reads) | C38: =MAX(0,C24-10000000)*Assumptions!C57/1000000 -> 0 | D38: =MAX(0,D24-10000000)*Assumptions!C57/1000000 -> 0 | E38: =MAX(0,E24-10000000)*Assumptions!C57/1000000 -> 0 | F38: =MAX(0,F24-10000000)*Assumptions!C57/1000000 -> 0 | G38: =MAX(0,G24-10000000)*Assumptions!C57/1000000 -> 0 | H38: =MAX(0,H24-10000000)*Assumptions!C57/1000000 -> 0 | I38: =MAX(0,I24-10000000)*Assumptions!C57/1000000 -> 0 | J38: =MAX(0,J24-10000000)*Assumptions!C57/1000000 -> 0 | K38: =MAX(0,K24-10000000)*Assumptions!C57/1000000 -> 0 | L38: =MAX(0,L24-10000000)*Assumptions!C57/1000000 -> 0 | M38: =MAX(0,M24-10000000)*Assumptions!C57/1000000 -> 0 | N38: =MAX(0,N24-10000000)*Assumptions!C57/1000000 -> 0 | O38: =MAX(0,O24-10000000)*Assumptions!C57/1000000 -> 0 | P38: =MAX(0,P24-10000000)*Assumptions!C57/1000000 -> 0 | Q38: =MAX(0,Q24-10000000)*Assumptions!C57/1000000 -> 0 | R38: =MAX(0,R24-10000000)*Assumptions!C57/1000000 -> 0 | S38: =MAX(0,S24-10000000)*Assumptions!C57/1000000 -> 0 | T38: =MAX(0,T24-10000000)*Assumptions!C57/1000000 -> 0 | U38: =MAX(0,U24-10000000)*Assumptions!C57/1000000 -> 0 | V38: =MAX(0,V24-10000000)*Assumptions!C57/1000000 -> 0 | W38: =MAX(0,W24-10000000)*Assumptions!C57/1000000 -> 0 | X38: =MAX(0,X24-10000000)*Assumptions!C57/1000000 -> 0 | Y38: =MAX(0,Y24-10000000)*Assumptions!C57/1000000 -> 0 | Z38: =MAX(0,Z24-10000000)*Assumptions!C57/1000000 -> 0
B39: Cloudflare R2 Total | C39: =C36+C37+C38 -> 0 | D39: =D36+D37+D38 -> 0 | E39: =E36+E37+E38 -> 0.07815 | F39: =F36+F37+F38 -> 0.168 | G39: =G36+G37+G38 -> 0.26595 | H39: =H36+H37+H38 -> 0.3729 | I39: =I36+I37+I38 -> 0.4893 | J39: =J36+J37+J38 -> 0.6165 | ... Z39: =Z36+Z37+Z38 -> 5.2593
B40: Azure Table Storage | C40: =(C11*Assumptions!C65/1024/1024)*Assumptions!C63+(C27/10000)*Assumptions!C64 -> 0.00021890565 | D40: =(D11*Assumptions!C65/1024/1024)*Assumptions!C63+(D27/10000)*Assumptions!C64 -> 0.00041956744 | E40: =(E11*Assumptions!C65/1024/1024)*Assumptions!C63+(E27/10000)*Assumptions!C64 -> 0.00063809886 | F40: =(F11*Assumptions!C65/1024/1024)*Assumptions!C63+(F27/10000)*Assumptions!C64 -> 0.00071925407 | G40: =(G11*Assumptions!C65/1024/1024)*Assumptions!C63+(G27/10000)*Assumptions!C64 -> 0.00083031675 | H40: =(H11*Assumptions!C65/1024/1024)*Assumptions!C63+(H27/10000)*Assumptions!C64 -> 0.00095219855 | I40: =(I11*Assumptions!C65/1024/1024)*Assumptions!C63+(I27/10000)*Assumptions!C64 -> 0.0010851791 | J40: =(J11*Assumptions!C65/1024/1024)*Assumptions!C63+(J27/10000)*Assumptions!C64 -> 0.0012306625 | K40: =(K11*Assumptions!C65/1024/1024)*Assumptions!C63+(K27/10000)*Assumptions!C64 -> 0.001389856 | L40: =(L11*Assumptions!C65/1024/1024)*Assumptions!C63+(L27/10000)*Assumptions!C64 -> 0.0015649334 | M40: =(M11*Assumptions!C65/1024/1024)*Assumptions!C63+(M27/10000)*Assumptions!C64 -> 0.0017545184 | N40: =(N11*Assumptions!C65/1024/1024)*Assumptions!C63+(N27/10000)*Assumptions!C64 -> 0.0019607266 | O40: =(O11*Assumptions!C65/1024/1024)*Assumptions!C63+(O27/10000)*Assumptions!C64 -> 0.0021841258 | P40: =(P11*Assumptions!C65/1024/1024)*Assumptions!C63+(P27/10000)*Assumptions!C64 -> 0.0024279393 | Q40: =(Q11*Assumptions!C65/1024/1024)*Assumptions!C63+(Q27/10000)*Assumptions!C64 -> 0.0026952324 | R40: =(R11*Assumptions!C65/1024/1024)*Assumptions!C63+(R27/10000)*Assumptions!C64 -> 0.0029881126 | S40: =(S11*Assumptions!C65/1024/1024)*Assumptions!C63+(S27/10000)*Assumptions!C64 -> 0.0033095014 | T40: =(T11*Assumptions!C65/1024/1024)*Assumptions!C63+(T27/10000)*Assumptions!C64 -> 0.0036605257 | U40: =(U11*Assumptions!C65/1024/1024)*Assumptions!C63+(U27/10000)*Assumptions!C64 -> 0.0040443951 | V40: =(V11*Assumptions!C65/1024/1024)*Assumptions!C63+(V27/10000)*Assumptions!C64 -> 0.0044622807 | W40: =(W11*Assumptions!C65/1024/1024)*Assumptions!C63+(W27/10000)*Assumptions!C64 -> 0.0049200174 | X40: =(X11*Assumptions!C65/1024/1024)*Assumptions!C63+(X27/10000)*Assumptions!C64 -> 0.0054213102 | Y40: =(Y11*Assumptions!C65/1024/1024)*Assumptions!C63+(Y27/10000)*Assumptions!C64 -> 0.0059696982 | Z40: =(Z11*Assumptions!C65/1024/1024)*Assumptions!C63+(Z27/10000)*Assumptions!C64 -> 0.0065690719
B41: Azure Functions (Compute) | C41: =MAX(0,C22-Assumptions!C73)/1000000*Assumptions!C69+MAX(0,C22*(Assumptions!C71/1000)*(Assumptions!C72/1024)-Assumptions!C74)*Assumptions!C70 -> 0 | D41: =MAX(0,D22-Assumptions!C73)/1000000*Assumptions!C69+MAX(0,D22*(Assumptions!C71/1000)*(Assumptions!C72/1024)-Assumptions!C74)*Assumptions!C70 -> 0 | E41: =MAX(0,E22-Assumptions!C73)/1000000*Assumptions!C69+MAX(0,E22*(Assumptions!C71/1000)*(Assumptions!C72/1024)-Assumptions!C74)*Assumptions!C70 -> 0 | F41: =MAX(0,F22-Assumptions!C73)/1000000*Assumptions!C69+MAX(0,F22*(Assumptions!C71/1000)*(Assumptions!C72/1024)-Assumptions!C74)*Assumptions!C70 -> 0 | G41: =MAX(0,G22-Assumptions!C73)/1000000*Assumptions!C69+MAX(0,G22*(Assumptions!C71/1000)*(Assumptions!C72/1024)-Assumptions!C74)*Assumptions!C70 -> 0 | H41: =MAX(0,H22-Assumptions!C73)/1000000*Assumptions!C69+MAX(0,H22*(Assumptions!C71/1000)*(Assumptions!C72/1024)-Assumptions!C74)*Assumptions!C70 -> 0 | I41: =MAX(0,I22-Assumptions!C73)/1000000*Assumptions!C69+MAX(0,I22*(Assumptions!C71/1000)*(Assumptions!C72/1024)-Assumptions!C74)*Assumptions!C70 -> 0 | J41: =MAX(0,J22-Assumptions!C73)/1000000*Assumptions!C69+MAX(0,J22*(Assumptions!C71/1000)*(Assumptions!C72/1024)-Assumptions!C74)*Assumptions!C70 -> 0 | K41: =MAX(0,K22-Assumptions!C73)/1000000*Assumptions!C69+MAX(0,K22*(Assumptions!C71/1000)*(Assumptions!C72/1024)-Assumptions!C74)*Assumptions!C70 -> 0 | L41: =MAX(0,L22-Assumptions!C73)/1000000*Assumptions!C69+MAX(0,L22*(Assumptions!C71/1000)*(Assumptions!C72/1024)-Assumptions!C74)*Assumptions!C70 -> 0 | M41: =MAX(0,M22-Assumptions!C73)/1000000*Assumptions!C69+MAX(0,M22*(Assumptions!C71/1000)*(Assumptions!C72/1024)-Assumptions!C74)*Assumptions!C70 -> 0 | N41: =MAX(0,N22-Assumptions!C73)/1000000*Assumptions!C69+MAX(0,N22*(Assumptions!C71/1000)*(Assumptions!C72/1024)-Assumptions!C74)*Assumptions!C70 -> 0 | O41: =MAX(0,O22-Assumptions!C73)/1000000*Assumptions!C69+MAX(0,O22*(Assumptions!C71/1000)*(Assumptions!C72/1024)-Assumptions!C74)*Assumptions!C70 -> 0 | P41: =MAX(0,P22-Assumptions!C73)/1000000*Assumptions!C69+MAX(0,P22*(Assumptions!C71/1000)*(Assumptions!C72/1024)-Assumptions!C74)*Assumptions!C70 -> 0 | Q41: =MAX(0,Q22-Assumptions!C73)/1000000*Assumptions!C69+MAX(0,Q22*(Assumptions!C71/1000)*(Assumptions!C72/1024)-Assumptions!C74)*Assumptions!C70 -> 0 | R41: =MAX(0,R22-Assumptions!C73)/1000000*Assumptions!C69+MAX(0,R22*(Assumptions!C71/1000)*(Assumptions!C72/1024)-Assumptions!C74)*Assumptions!C70 -> 0 | S41: =MAX(0,S22-Assumptions!C73)/1000000*Assumptions!C69+MAX(0,S22*(Assumptions!C71/1000)*(Assumptions!C72/1024)-Assumptions!C74)*Assumptions!C70 -> 0 | T41: =MAX(0,T22-Assumptions!C73)/1000000*Assumptions!C69+MAX(0,T22*(Assumptions!C71/1000)*(Assumptions!C72/1024)-Assumptions!C74)*Assumptions!C70 -> 0 | U41: =MAX(0,U22-Assumptions!C73)/1000000*Assumptions!C69+MAX(0,U22*(Assumptions!C71/1000)*(Assumptions!C72/1024)-Assumptions!C74)*Assumptions!C70 -> 0 | V41: =MAX(0,V22-Assumptions!C73)/1000000*Assumptions!C69+MAX(0,V22*(Assumptions!C71/1000)*(Assumptions!C72/1024)-Assumptions!C74)*Assumptions!C70 -> 0 | W41: =MAX(0,W22-Assumptions!C73)/1000000*Assumptions!C69+MAX(0,W22*(Assumptions!C71/1000)*(Assumptions!C72/1024)-Assumptions!C74)*Assumptions!C70 -> 0 | X41: =MAX(0,X22-Assumptions!C73)/1000000*Assumptions!C69+MAX(0,X22*(Assumptions!C71/1000)*(Assumptions!C72/1024)-Assumptions!C74)*Assumptions!C70 -> 0 | Y41: =MAX(0,Y22-Assumptions!C73)/1000000*Assumptions!C69+MAX(0,Y22*(Assumptions!C71/1000)*(Assumptions!C72/1024)-Assumptions!C74)*Assumptions!C70 -> 0 | Z41: =MAX(0,Z22-Assumptions!C73)/1000000*Assumptions!C69+MAX(0,Z22*(Assumptions!C71/1000)*(Assumptions!C72/1024)-Assumptions!C74)*Assumptions!C70 -> 0
B42: Other Platform (CIAM + DNS + Monitoring) | C42: =Assumptions!C78+MAX(0,C11*0.3-50000)*Assumptions!C79+Assumptions!C80+Assumptions!C81 -> 25 | D42: =Assumptions!C78+MAX(0,D11*0.3-50000)*Assumptions!C79+Assumptions!C80+Assumptions!C81 -> 25 | E42: =Assumptions!C78+MAX(0,E11*0.3-50000)*Assumptions!C79+Assumptions!C80+Assumptions!C81 -> 25 | F42: =Assumptions!C78+MAX(0,F11*0.3-50000)*Assumptions!C79+Assumptions!C80+Assumptions!C81 -> 25 | G42: =Assumptions!C78+MAX(0,G11*0.3-50000)*Assumptions!C79+Assumptions!C80+Assumptions!C81 -> 25 | H42: =Assumptions!C78+MAX(0,H11*0.3-50000)*Assumptions!C79+Assumptions!C80+Assumptions!C81 -> 25 | I42: =Assumptions!C78+MAX(0,I11*0.3-50000)*Assumptions!C79+Assumptions!C80+Assumptions!C81 -> 25 | J42: =Assumptions!C78+MAX(0,J11*0.3-50000)*Assumptions!C79+Assumptions!C80+Assumptions!C81 -> 25 | K42: =Assumptions!C78+MAX(0,K11*0.3-50000)*Assumptions!C79+Assumptions!C80+Assumptions!C81 -> 25 | L42: =Assumptions!C78+MAX(0,L11*0.3-50000)*Assumptions!C79+Assumptions!C80+Assumptions!C81 -> 25 | M42: =Assumptions!C78+MAX(0,M11*0.3-50000)*Assumptions!C79+Assumptions!C80+Assumptions!C81 -> 25 | N42: =Assumptions!C78+MAX(0,N11*0.3-50000)*Assumptions!C79+Assumptions!C80+Assumptions!C81 -> 25 | O42: =Assumptions!C78+MAX(0,O11*0.3-50000)*Assumptions!C79+Assumptions!C80+Assumptions!C81 -> 25 | P42: =Assumptions!C78+MAX(0,P11*0.3-50000)*Assumptions!C79+Assumptions!C80+Assumptions!C81 -> 25 | Q42: =Assumptions!C78+MAX(0,Q11*0.3-50000)*Assumptions!C79+Assumptions!C80+Assumptions!C81 -> 25 | R42: =Assumptions!C78+MAX(0,R11*0.3-50000)*Assumptions!C79+Assumptions!C80+Assumptions!C81 -> 25 | S42: =Assumptions!C78+MAX(0,S11*0.3-50000)*Assumptions!C79+Assumptions!C80+Assumptions!C81 -> 25 | T42: =Assumptions!C78+MAX(0,T11*0.3-50000)*Assumptions!C79+Assumptions!C80+Assumptions!C81 -> 25 | U42: =Assumptions!C78+MAX(0,U11*0.3-50000)*Assumptions!C79+Assumptions!C80+Assumptions!C81 -> 25 | V42: =Assumptions!C78+MAX(0,V11*0.3-50000)*Assumptions!C79+Assumptions!C80+Assumptions!C81 -> 25 | W42: =Assumptions!C78+MAX(0,W11*0.3-50000)*Assumptions!C79+Assumptions!C80+Assumptions!C81 -> 25 | X42: =Assumptions!C78+MAX(0,X11*0.3-50000)*Assumptions!C79+Assumptions!C80+Assumptions!C81 -> 25 | Y42: =Assumptions!C78+MAX(0,Y11*0.3-50000)*Assumptions!C79+Assumptions!C80+Assumptions!C81 -> 25 | Z42: =Assumptions!C78+MAX(0,Z11*0.3-50000)*Assumptions!C79+Assumptions!C80+Assumptions!C81 -> 25
B43: TOTAL INFRASTRUCTURE | C43: =C35+C39+C40+C41+C42 -> 25.058617 | D43: =D35+D39+D40+D41+D42 -> 25.119254 | E43: =E35+E39+E40+E41+E42 -> 25.263275 | F43: =F35+F39+F40+F41+F42 -> 25.416618 | G43: =G35+G39+G40+G41+G42 -> 25.585298 | H43: =H35+H39+H40+H41+H42 -> 25.76903 | I43: =I35+I39+I40+I41+I42 -> 25.969239 | J43: =J35+J39+J40+J41+J42 -> 26.188239 | ... Z43: =Z35+Z39+Z40+Z41+Z42 -> 34.175278
B45: REVENUE
B46: 10-Year Charm Revenue | C46: =C6*Assumptions!C6 -> 2999 | D46: =D6*Assumptions!C6 -> 3238.92 | E46: =E6*Assumptions!C6 -> 3508.83 | F46: =F6*Assumptions!C6 -> 3778.74 | G46: =G6*Assumptions!C6 -> 4078.64 | H46: =H6*Assumptions!C6 -> 4408.53 | I46: =I6*Assumptions!C6 -> 4768.41 | J46: =J6*Assumptions!C6 -> 5158.28 | K46: =K6*Assumptions!C6 -> 5578.14 | L46: =L6*Assumptions!C6 -> 6027.99 | M46: =M6*Assumptions!C6 -> 6507.83 | N46: =N6*Assumptions!C6 -> 7017.66 | O46: =O6*Assumptions!C6 -> 7587.47 | P46: =P6*Assumptions!C6 -> 8187.27 | Q46: =Q6*Assumptions!C6 -> 8847.05 | R46: =R6*Assumptions!C6 -> 9566.81 | S46: =S6*Assumptions!C6 -> 10346.55 | T46: =T6*Assumptions!C6 -> 11186.27 | U46: =U6*Assumptions!C6 -> 12085.97 | V46: =V6*Assumptions!C6 -> 13045.65 | W46: =W6*Assumptions!C6 -> 14095.3 | X46: =X6*Assumptions!C6 -> 15234.92 | Y46: =Y6*Assumptions!C6 -> 16464.51 | Z46: =Z6*Assumptions!C6 -> 17784.07
B47: 15-Year Charm Revenue | C47: =C7*Assumptions!C7 -> 1799.6 | D47: =D7*Assumptions!C7 -> 1979.56 | E47: =E7*Assumptions!C7 -> 2159.52 | F47: =F7*Assumptions!C7 -> 2384.47 | G47: =G7*Assumptions!C7 -> 2609.42 | H47: =H7*Assumptions!C7 -> 2879.36 | I47: =I7*Assumptions!C7 -> 3149.3 | J47: =J7*Assumptions!C7 -> 3464.23 | K47: =K7*Assumptions!C7 -> 3824.15 | L47: =L7*Assumptions!C7 -> 4229.06 | M47: =M7*Assumptions!C7 -> 4633.97 | N47: =N7*Assumptions!C7 -> 5083.87 | O47: =O7*Assumptions!C7 -> 5578.76 | P47: =P7*Assumptions!C7 -> 6118.64 | Q47: =Q7*Assumptions!C7 -> 6748.5 | R47: =R7*Assumptions!C7 -> 7423.35 | S47: =S7*Assumptions!C7 -> 8188.18 | T47: =T7*Assumptions!C7 -> 8998 | U47: =U7*Assumptions!C7 -> 9897.8 | V47: =V7*Assumptions!C7 -> 10887.58 | W47: =W7*Assumptions!C7 -> 11967.34 | X47: =X7*Assumptions!C7 -> 13182.07 | Y47: =Y7*Assumptions!C7 -> 14486.78 | Z47: =Z7*Assumptions!C7 -> 15926.46
B48: Retail (Perpetual) Charm Revenue | C48: =C8*Assumptions!C8 -> 1049.85 | D48: =D8*Assumptions!C8 -> 1189.83 | E48: =E8*Assumptions!C8 -> 1329.81 | F48: =F8*Assumptions!C8 -> 1469.79 | G48: =G8*Assumptions!C8 -> 1679.76 | H48: =H8*Assumptions!C8 -> 1889.73 | I48: =I8*Assumptions!C8 -> 2099.7 | J48: =J8*Assumptions!C8 -> 2379.66 | K48: =K8*Assumptions!C8 -> 2659.62 | L48: =L8*Assumptions!C8 -> 3009.57 | M48: =M8*Assumptions!C8 -> 3359.52 | N48: =N8*Assumptions!C8 -> 3779.46 | O48: =O8*Assumptions!C8 -> 4199.4 | P48: =P8*Assumptions!C8 -> 4689.33 | Q48: =Q8*Assumptions!C8 -> 5249.25 | R48: =R8*Assumptions!C8 -> 5879.16 | S48: =S8*Assumptions!C8 -> 6579.06 | T48: =T8*Assumptions!C8 -> 7348.95 | U48: =U8*Assumptions!C8 -> 8258.82 | V48: =V8*Assumptions!C8 -> 9238.68 | W48: =W8*Assumptions!C8 -> 10358.52 | X48: =X8*Assumptions!C8 -> 11618.34 | Y48: =Y8*Assumptions!C8 -> 13018.14 | Z48: =Z8*Assumptions!C8 -> 14557.92
B49: Extend Memory Revenue | C49: =ROUND(C10*Assumptions!C23,0)*Assumptions!C12 -> 44.97 | D49: =ROUND(D10*Assumptions!C23,0)*Assumptions!C12 -> 89.94 | E49: =ROUND(E10*Assumptions!C23,0)*Assumptions!C12 -> 149.9 | F49: =ROUND(F10*Assumptions!C23,0)*Assumptions!C12 -> 209.86 | G49: =ROUND(G10*Assumptions!C23,0)*Assumptions!C12 -> 284.81 | H49: =ROUND(H10*Assumptions!C23,0)*Assumptions!C12 -> 344.77 | I49: =ROUND(I10*Assumptions!C23,0)*Assumptions!C12 -> 419.72 | J49: =ROUND(J10*Assumptions!C23,0)*Assumptions!C12 -> 509.66 | K49: =ROUND(K10*Assumptions!C23,0)*Assumptions!C12 -> 599.6 | L49: =ROUND(L10*Assumptions!C23,0)*Assumptions!C12 -> 704.53 | M49: =ROUND(M10*Assumptions!C23,0)*Assumptions!C12 -> 809.46 | N49: =ROUND(N10*Assumptions!C23,0)*Assumptions!C12 -> 929.38 | O49: =ROUND(O10*Assumptions!C23,0)*Assumptions!C12 -> 1064.29 | P49: =ROUND(P10*Assumptions!C23,0)*Assumptions!C12 -> 1214.19 | Q49: =ROUND(Q10*Assumptions!C23,0)*Assumptions!C12 -> 1364.09 | R49: =ROUND(R10*Assumptions!C23,0)*Assumptions!C12 -> 1528.98 | S49: =ROUND(S10*Assumptions!C23,0)*Assumptions!C12 -> 1723.85 | T49: =ROUND(T10*Assumptions!C23,0)*Assumptions!C12 -> 1918.72 | U49: =ROUND(U10*Assumptions!C23,0)*Assumptions!C12 -> 2143.57 | V49: =ROUND(V10*Assumptions!C23,0)*Assumptions!C12 -> 2383.41 | W49: =ROUND(W10*Assumptions!C23,0)*Assumptions!C12 -> 2653.23 | X49: =ROUND(X10*Assumptions!C23,0)*Assumptions!C12 -> 2938.04 | Y49: =ROUND(Y10*Assumptions!C23,0)*Assumptions!C12 -> 3267.82 | Z49: =ROUND(Z10*Assumptions!C23,0)*Assumptions!C12 -> 3612.59
B50: Upgrade Tier Revenue | C50: =ROUND(C10*Assumptions!C24,0)*Assumptions!C13 -> 39.98 | D50: =ROUND(D10*Assumptions!C24,0)*Assumptions!C13 -> 59.97 | E50: =ROUND(E10*Assumptions!C24,0)*Assumptions!C13 -> 99.95 | F50: =ROUND(F10*Assumptions!C24,0)*Assumptions!C13 -> 139.93 | G50: =ROUND(G10*Assumptions!C24,0)*Assumptions!C13 -> 179.91 | H50: =ROUND(H10*Assumptions!C24,0)*Assumptions!C13 -> 239.88 | I50: =ROUND(I10*Assumptions!C24,0)*Assumptions!C13 -> 279.86 | J50: =ROUND(J10*Assumptions!C24,0)*Assumptions!C13 -> 339.83 | K50: =ROUND(K10*Assumptions!C24,0)*Assumptions!C13 -> 399.8 | L50: =ROUND(L10*Assumptions!C24,0)*Assumptions!C13 -> 479.76 | M50: =ROUND(M10*Assumptions!C24,0)*Assumptions!C13 -> 539.73 | N50: =ROUND(N10*Assumptions!C24,0)*Assumptions!C13 -> 619.69 | O50: =ROUND(O10*Assumptions!C24,0)*Assumptions!C13 -> 719.64 | P50: =ROUND(P10*Assumptions!C24,0)*Assumptions!C13 -> 799.6 | Q50: =ROUND(Q10*Assumptions!C24,0)*Assumptions!C13 -> 919.54 | R50: =ROUND(R10*Assumptions!C24,0)*Assumptions!C13 -> 1019.49 | S50: =ROUND(S10*Assumptions!C24,0)*Assumptions!C13 -> 1139.43 | T50: =ROUND(T10*Assumptions!C24,0)*Assumptions!C13 -> 1279.36 | U50: =ROUND(U10*Assumptions!C24,0)*Assumptions!C13 -> 1439.28 | V50: =ROUND(V10*Assumptions!C24,0)*Assumptions!C13 -> 1599.2 | W50: =ROUND(W10*Assumptions!C24,0)*Assumptions!C13 -> 1779.11 | X50: =ROUND(X10*Assumptions!C24,0)*Assumptions!C13 -> 1959.02 | Y50: =ROUND(Y10*Assumptions!C24,0)*Assumptions!C13 -> 2178.91 | Z50: =ROUND(Z10*Assumptions!C24,0)*Assumptions!C13 -> 2398.8
B51: Gift Wrap Revenue | C51: =ROUND(C9*Assumptions!C25,0)*Assumptions!C14 -> 114.77 | D51: =ROUND(D9*Assumptions!C25,0)*Assumptions!C14 -> 124.75 | E51: =ROUND(E9*Assumptions!C25,0)*Assumptions!C14 -> 139.72 | F51: =ROUND(F9*Assumptions!C25,0)*Assumptions!C14 -> 149.7 | G51: =ROUND(G9*Assumptions!C25,0)*Assumptions!C14 -> 164.67 | H51: =ROUND(H9*Assumptions!C25,0)*Assumptions!C14 -> 179.64 | I51: =ROUND(I9*Assumptions!C25,0)*Assumptions!C14 -> 194.61 | J51: =ROUND(J9*Assumptions!C25,0)*Assumptions!C14 -> 209.58 | K51: =ROUND(K9*Assumptions!C25,0)*Assumptions!C14 -> 229.54 | L51: =ROUND(L9*Assumptions!C25,0)*Assumptions!C14 -> 254.49 | M51: =ROUND(M9*Assumptions!C25,0)*Assumptions!C14 -> 274.45 | N51: =ROUND(N9*Assumptions!C25,0)*Assumptions!C14 -> 299.4 | O51: =ROUND(O9*Assumptions!C25,0)*Assumptions!C14 -> 329.34 | P51: =ROUND(P9*Assumptions!C25,0)*Assumptions!C14 -> 354.29 | Q51: =ROUND(Q9*Assumptions!C25,0)*Assumptions!C14 -> 389.22 | R51: =ROUND(R9*Assumptions!C25,0)*Assumptions!C14 -> 424.15 | S51: =ROUND(S9*Assumptions!C25,0)*Assumptions!C14 -> 464.07 | T51: =ROUND(T9*Assumptions!C25,0)*Assumptions!C14 -> 508.98 | U51: =ROUND(U9*Assumptions!C25,0)*Assumptions!C14 -> 553.89 | V51: =ROUND(V9*Assumptions!C25,0)*Assumptions!C14 -> 603.79 | W51: =ROUND(W9*Assumptions!C25,0)*Assumptions!C14 -> 663.67 | X51: =ROUND(X9*Assumptions!C25,0)*Assumptions!C14 -> 723.55 | Y51: =ROUND(Y9*Assumptions!C25,0)*Assumptions!C14 -> 793.41 | Z51: =ROUND(Z9*Assumptions!C25,0)*Assumptions!C14 -> 863.27
B52: TOTAL REVENUE | C52: =SUM(C46:C51) -> 6048.17 | D52: =SUM(D46:D51) -> 6682.97 | E52: =SUM(E46:E51) -> 7387.73 | F52: =SUM(F46:F51) -> 8132.49 | G52: =SUM(G46:G51) -> 8997.21 | H52: =SUM(H46:H51) -> 9941.91 | I52: =SUM(I46:I51) -> 10911.6 | J52: =SUM(J46:J51) -> 12061.24 | ... Z52: =SUM(Z46:Z51) -> 55143.11
B54: COST OF GOODS SOLD
B55: 10-Year Charm COGS | C55: =C6*Assumptions!D6 -> 850 | D55: =D6*Assumptions!D6 -> 918 | E55: =E6*Assumptions!D6 -> 994.5 | F55: =F6*Assumptions!D6 -> 1071 | G55: =G6*Assumptions!D6 -> 1156 | H55: =H6*Assumptions!D6 -> 1249.5 | I55: =I6*Assumptions!D6 -> 1351.5 | J55: =J6*Assumptions!D6 -> 1462 | K55: =K6*Assumptions!D6 -> 1581 | L55: =L6*Assumptions!D6 -> 1708.5 | M55: =M6*Assumptions!D6 -> 1844.5 | N55: =N6*Assumptions!D6 -> 1989 | O55: =O6*Assumptions!D6 -> 2150.5 | P55: =P6*Assumptions!D6 -> 2320.5 | Q55: =Q6*Assumptions!D6 -> 2507.5 | R55: =R6*Assumptions!D6 -> 2711.5 | S55: =S6*Assumptions!D6 -> 2932.5 | T55: =T6*Assumptions!D6 -> 3170.5 | U55: =U6*Assumptions!D6 -> 3425.5 | V55: =V6*Assumptions!D6 -> 3697.5 | W55: =W6*Assumptions!D6 -> 3995 | X55: =X6*Assumptions!D6 -> 4318 | Y55: =Y6*Assumptions!D6 -> 4666.5 | Z55: =Z6*Assumptions!D6 -> 5040.5
B56: 15-Year Charm COGS | C56: =C7*Assumptions!D7 -> 340 | D56: =D7*Assumptions!D7 -> 374 | E56: =E7*Assumptions!D7 -> 408 | F56: =F7*Assumptions!D7 -> 450.5 | G56: =G7*Assumptions!D7 -> 493 | H56: =H7*Assumptions!D7 -> 544 | I56: =I7*Assumptions!D7 -> 595 | J56: =J7*Assumptions!D7 -> 654.5 | K56: =K7*Assumptions!D7 -> 722.5 | L56: =L7*Assumptions!D7 -> 799 | M56: =M7*Assumptions!D7 -> 875.5 | N56: =N7*Assumptions!D7 -> 960.5 | O56: =O7*Assumptions!D7 -> 1054 | P56: =P7*Assumptions!D7 -> 1156 | Q56: =Q7*Assumptions!D7 -> 1275 | R56: =R7*Assumptions!D7 -> 1402.5 | S56: =S7*Assumptions!D7 -> 1547 | T56: =T7*Assumptions!D7 -> 1700 | U56: =U7*Assumptions!D7 -> 1870 | V56: =V7*Assumptions!D7 -> 2057 | W56: =W7*Assumptions!D7 -> 2261 | X56: =X7*Assumptions!D7 -> 2490.5 | Y56: =Y7*Assumptions!D7 -> 2737 | Z56: =Z7*Assumptions!D7 -> 3009
B57: Retail (Perpetual) Charm COGS | C57: =C8*Assumptions!D8 -> 135 | D57: =D8*Assumptions!D8 -> 153 | E57: =E8*Assumptions!D8 -> 171 | F57: =F8*Assumptions!D8 -> 189 | G57: =G8*Assumptions!D8 -> 216 | H57: =H8*Assumptions!D8 -> 243 | I57: =I8*Assumptions!D8 -> 270 | J57: =J8*Assumptions!D8 -> 306 | K57: =K8*Assumptions!D8 -> 342 | L57: =L8*Assumptions!D8 -> 387 | M57: =M8*Assumptions!D8 -> 432 | N57: =N8*Assumptions!D8 -> 486 | O57: =O8*Assumptions!D8 -> 540 | P57: =P8*Assumptions!D8 -> 603 | Q57: =Q8*Assumptions!D8 -> 675 | R57: =R8*Assumptions!D8 -> 756 | S57: =S8*Assumptions!D8 -> 846 | T57: =T8*Assumptions!D8 -> 945 | U57: =U8*Assumptions!D8 -> 1062 | V57: =V8*Assumptions!D8 -> 1188 | W57: =W8*Assumptions!D8 -> 1332 | X57: =X8*Assumptions!D8 -> 1494 | Y57: =Y8*Assumptions!D8 -> 1674 | Z57: =Z8*Assumptions!D8 -> 1872
B58: Upsell COGS | C58: =ROUND(C10*Assumptions!C23,0)*Assumptions!D12+ROUND(C10*Assumptions!C24,0)*Assumptions!D13+ROUND(C9*Assumptions!C25,0)*Assumptions!D14 -> 38.5 | D58: =ROUND(D10*Assumptions!C23,0)*Assumptions!D12+ROUND(D10*Assumptions!C24,0)*Assumptions!D13+ROUND(D9*Assumptions!C25,0)*Assumptions!D14 -> 45 | E58: =ROUND(E10*Assumptions!C23,0)*Assumptions!D12+ROUND(E10*Assumptions!C24,0)*Assumptions!D13+ROUND(E9*Assumptions!C25,0)*Assumptions!D14 -> 54.5 | F58: =ROUND(F10*Assumptions!C23,0)*Assumptions!D12+ROUND(F10*Assumptions!C24,0)*Assumptions!D13+ROUND(F9*Assumptions!C25,0)*Assumptions!D14 -> 62.5 | G58: =ROUND(G10*Assumptions!C23,0)*Assumptions!D12+ROUND(G10*Assumptions!C24,0)*Assumptions!D13+ROUND(G9*Assumptions!C25,0)*Assumptions!D14 -> 73 | H58: =ROUND(H10*Assumptions!C23,0)*Assumptions!D12+ROUND(H10*Assumptions!C24,0)*Assumptions!D13+ROUND(H9*Assumptions!C25,0)*Assumptions!D14 -> 83 | I58: =ROUND(I10*Assumptions!C23,0)*Assumptions!D12+ROUND(I10*Assumptions!C24,0)*Assumptions!D13+ROUND(I9*Assumptions!C25,0)*Assumptions!D14 -> 93.5 | J58: =ROUND(J10*Assumptions!C23,0)*Assumptions!D12+ROUND(J10*Assumptions!C24,0)*Assumptions!D13+ROUND(J9*Assumptions!C25,0)*Assumptions!D14 -> 105.5 | K58: =ROUND(K10*Assumptions!C23,0)*Assumptions!D12+ROUND(K10*Assumptions!C24,0)*Assumptions!D13+ROUND(K9*Assumptions!C25,0)*Assumptions!D14 -> 119 | L58: =ROUND(L10*Assumptions!C23,0)*Assumptions!D12+ROUND(L10*Assumptions!C24,0)*Assumptions!D13+ROUND(L9*Assumptions!C25,0)*Assumptions!D14 -> 135.5 | M58: =ROUND(M10*Assumptions!C23,0)*Assumptions!D12+ROUND(M10*Assumptions!C24,0)*Assumptions!D13+ROUND(M9*Assumptions!C25,0)*Assumptions!D14 -> 150 | N58: =ROUND(N10*Assumptions!C23,0)*Assumptions!D12+ROUND(N10*Assumptions!C24,0)*Assumptions!D13+ROUND(N9*Assumptions!C25,0)*Assumptions!D14 -> 167.5 | O58: =ROUND(O10*Assumptions!C23,0)*Assumptions!D12+ROUND(O10*Assumptions!C24,0)*Assumptions!D13+ROUND(O9*Assumptions!C25,0)*Assumptions!D14 -> 188 | P58: =ROUND(P10*Assumptions!C23,0)*Assumptions!D12+ROUND(P10*Assumptions!C24,0)*Assumptions!D13+ROUND(P9*Assumptions!C25,0)*Assumptions!D14 -> 207.5 | Q58: =ROUND(Q10*Assumptions!C23,0)*Assumptions!D12+ROUND(Q10*Assumptions!C24,0)*Assumptions!D13+ROUND(Q9*Assumptions!C25,0)*Assumptions!D14 -> 231 | R58: =ROUND(R10*Assumptions!C23,0)*Assumptions!D12+ROUND(R10*Assumptions!C24,0)*Assumptions!D13+ROUND(R9*Assumptions!C25,0)*Assumptions!D14 -> 255 | S58: =ROUND(S10*Assumptions!C23,0)*Assumptions!D12+ROUND(S10*Assumptions!C24,0)*Assumptions!D13+ROUND(S9*Assumptions!C25,0)*Assumptions!D14 -> 283 | T58: =ROUND(T10*Assumptions!C23,0)*Assumptions!D12+ROUND(T10*Assumptions!C24,0)*Assumptions!D13+ROUND(T9*Assumptions!C25,0)*Assumptions!D14 -> 313 | U58: =ROUND(U10*Assumptions!C23,0)*Assumptions!D12+ROUND(U10*Assumptions!C24,0)*Assumptions!D13+ROUND(U9*Assumptions!C25,0)*Assumptions!D14 -> 345.5 | V58: =ROUND(V10*Assumptions!C23,0)*Assumptions!D12+ROUND(V10*Assumptions!C24,0)*Assumptions!D13+ROUND(V9*Assumptions!C25,0)*Assumptions!D14 -> 380.5 | W58: =ROUND(W10*Assumptions!C23,0)*Assumptions!D12+ROUND(W10*Assumptions!C24,0)*Assumptions!D13+ROUND(W9*Assumptions!C25,0)*Assumptions!D14 -> 421 | X58: =ROUND(X10*Assumptions!C23,0)*Assumptions!D12+ROUND(X10*Assumptions!C24,0)*Assumptions!D13+ROUND(X9*Assumptions!C25,0)*Assumptions!D14 -> 462.5 | Y58: =ROUND(Y10*Assumptions!C23,0)*Assumptions!D12+ROUND(Y10*Assumptions!C24,0)*Assumptions!D13+ROUND(Y9*Assumptions!C25,0)*Assumptions!D14 -> 511 | Z58: =ROUND(Z10*Assumptions!C23,0)*Assumptions!D12+ROUND(Z10*Assumptions!C24,0)*Assumptions!D13+ROUND(Z9*Assumptions!C25,0)*Assumptions!D14 -> 560.5
B59: TOTAL COGS | C59: =SUM(C55:C58) -> 1363.5 | D59: =SUM(D55:D58) -> 1490 | E59: =SUM(E55:E58) -> 1628 | F59: =SUM(F55:F58) -> 1773 | G59: =SUM(G55:G58) -> 1938 | H59: =SUM(H55:H58) -> 2119.5 | I59: =SUM(I55:I58) -> 2310 | J59: =SUM(J55:J58) -> 2528 | ... Z59: =SUM(Z55:Z58) -> 10482
B60: GROSS PROFIT | C60: =C52-C59 -> 4684.67 | D60: =D52-D59 -> 5192.97 | E60: =E52-E59 -> 5759.73 | F60: =F52-F59 -> 6359.49 | G60: =G52-G59 -> 7059.21 | H60: =H52-H59 -> 7822.41 | I60: =I52-I59 -> 8601.6 | J60: =J52-J59 -> 9533.24 | ... Z60: =Z52-Z59 -> 44661.11
B61: Gross Margin % | C61: =IF(C52>0,C60/C52,0) -> 0.77455991 | D61: =IF(D52>0,D60/D52,0) -> 0.77704524 | E61: =IF(E52>0,E60/E52,0) -> 0.77963461 | F61: =IF(F52>0,F60/F52,0) -> 0.78198559 | G61: =IF(G52>0,G60/G52,0) -> 0.78459989 | H61: =IF(H52>0,H60/H52,0) -> 0.78681159 | I61: =IF(I52>0,I60/I52,0) -> 0.78829869 | J61: =IF(J52>0,J60/J52,0) -> 0.79040298 | ... Z61: =IF(Z52>0,Z60/Z52,0) -> 0.80991279
B63: OPERATING EXPENSES
B64: Infrastructure (see breakdown above) | C64: =C43 -> 25.058617 | D64: =D43 -> 25.119254 | E64: =E43 -> 25.263275 | F64: =F43 -> 25.416618 | G64: =G43 -> 25.585298 | H64: =H43 -> 25.76903 | I64: =I43 -> 25.969239 | J64: =J43 -> 26.188239 | ... Z64: =Z43 -> 34.175278
B65: Marketing / Customer Acquisition | C65: =Assumptions!C85 -> 500 | D65: =ROUND(C65*(1+Assumptions!D85),0) -> 525 | E65: =ROUND(D65*(1+Assumptions!D85),0) -> 551 | F65: =ROUND(E65*(1+Assumptions!D85),0) -> 579 | G65: =ROUND(F65*(1+Assumptions!D85),0) -> 608 | H65: =ROUND(G65*(1+Assumptions!D85),0) -> 638 | I65: =ROUND(H65*(1+Assumptions!D85),0) -> 670 | J65: =ROUND(I65*(1+Assumptions!D85),0) -> 704 | K65: =ROUND(J65*(1+Assumptions!D85),0) -> 739 | L65: =ROUND(K65*(1+Assumptions!D85),0) -> 776 | M65: =ROUND(L65*(1+Assumptions!D85),0) -> 815 | N65: =ROUND(M65*(1+Assumptions!D85),0) -> 856 | O65: =ROUND(N65*(1+Assumptions!D85),0) -> 899 | P65: =ROUND(O65*(1+Assumptions!D85),0) -> 944 | Q65: =ROUND(P65*(1+Assumptions!D85),0) -> 991 | R65: =ROUND(Q65*(1+Assumptions!D85),0) -> 1041 | S65: =ROUND(R65*(1+Assumptions!D85),0) -> 1093 | T65: =ROUND(S65*(1+Assumptions!D85),0) -> 1148 | U65: =ROUND(T65*(1+Assumptions!D85),0) -> 1205 | V65: =ROUND(U65*(1+Assumptions!D85),0) -> 1265 | W65: =ROUND(V65*(1+Assumptions!D85),0) -> 1328 | X65: =ROUND(W65*(1+Assumptions!D85),0) -> 1394 | Y65: =ROUND(X65*(1+Assumptions!D85),0) -> 1464 | Z65: =ROUND(Y65*(1+Assumptions!D85),0) -> 1537
B66: Shipping & Fulfillment | C66: =C9*Assumptions!C86 -> 542.5 | D66: =D9*Assumptions!C86 -> 591.5 | E66: =E9*Assumptions!C86 -> 644 | F66: =F9*Assumptions!C86 -> 700 | G66: =G9*Assumptions!C86 -> 763 | H66: =H9*Assumptions!C86 -> 833 | I66: =I9*Assumptions!C86 -> 906.5 | J66: =J9*Assumptions!C86 -> 990.5 | K66: =K9*Assumptions!C86 -> 1081.5 | L66: =L9*Assumptions!C86 -> 1183 | M66: =M9*Assumptions!C86 -> 1288 | N66: =N9*Assumptions!C86 -> 1403.5 | O66: =O9*Assumptions!C86 -> 1529.5 | P66: =P9*Assumptions!C86 -> 1666 | Q66: =Q9*Assumptions!C86 -> 1820 | R66: =R9*Assumptions!C86 -> 1988 | S66: =S9*Assumptions!C86 -> 2173.5 | T66: =T9*Assumptions!C86 -> 2373 | U66: =U9*Assumptions!C86 -> 2593.5 | V66: =V9*Assumptions!C86 -> 2831.5 | W66: =W9*Assumptions!C86 -> 3094 | X66: =X9*Assumptions!C86 -> 3384.5 | Y66: =Y9*Assumptions!C86 -> 3699.5 | Z66: =Z9*Assumptions!C86 -> 4042.5
B67: Payment Processing | C67: =C52*Assumptions!C87 -> 175.39693 | D67: =D52*Assumptions!C87 -> 193.80613 | E67: =E52*Assumptions!C87 -> 214.24417 | F67: =F52*Assumptions!C87 -> 235.84221 | G67: =G52*Assumptions!C87 -> 260.91909 | H67: =H52*Assumptions!C87 -> 288.31539 | I67: =I52*Assumptions!C87 -> 316.4364 | J67: =J52*Assumptions!C87 -> 349.77596 | K67: =K52*Assumptions!C87 -> 385.43465 | L67: =L52*Assumptions!C87 -> 426.4566 | M67: =M52*Assumptions!C87 -> 467.62384 | N67: =N52*Assumptions!C87 -> 514.15434 | O67: =O52*Assumptions!C87 -> 564.8881 | P67: =P52*Assumptions!C87 -> 619.53628 | Q67: =Q52*Assumptions!C87 -> 682.01185 | R67: =R52*Assumptions!C87 -> 749.41626 | S67: =S52*Assumptions!C87 -> 824.79306 | T67: =T52*Assumptions!C87 -> 905.96812 | U67: =U52*Assumptions!C87 -> 997.00057 | V67: =V52*Assumptions!C87 -> 1094.991 | W67: =W52*Assumptions!C87 -> 1203.9979 | X67: =X52*Assumptions!C87 -> 1324.0223 | Y67: =Y52*Assumptions!C87 -> 1456.0775 | Z67: =Z52*Assumptions!C87 -> 1599.1502
B68: Customer Support | C68: =Assumptions!C88 -> 200 | D68: =ROUND(C68*(1+Assumptions!D88),0) -> 206 | E68: =ROUND(D68*(1+Assumptions!D88),0) -> 212 | F68: =ROUND(E68*(1+Assumptions!D88),0) -> 218 | G68: =ROUND(F68*(1+Assumptions!D88),0) -> 225 | H68: =ROUND(G68*(1+Assumptions!D88),0) -> 232 | I68: =ROUND(H68*(1+Assumptions!D88),0) -> 239 | J68: =ROUND(I68*(1+Assumptions!D88),0) -> 246 | K68: =ROUND(J68*(1+Assumptions!D88),0) -> 253 | L68: =ROUND(K68*(1+Assumptions!D88),0) -> 261 | M68: =ROUND(L68*(1+Assumptions!D88),0) -> 269 | N68: =ROUND(M68*(1+Assumptions!D88),0) -> 277 | O68: =ROUND(N68*(1+Assumptions!D88),0) -> 285 | P68: =ROUND(O68*(1+Assumptions!D88),0) -> 294 | Q68: =ROUND(P68*(1+Assumptions!D88),0) -> 303 | R68: =ROUND(Q68*(1+Assumptions!D88),0) -> 312 | S68: =ROUND(R68*(1+Assumptions!D88),0) -> 321 | T68: =ROUND(S68*(1+Assumptions!D88),0) -> 331 | U68: =ROUND(T68*(1+Assumptions!D88),0) -> 341 | V68: =ROUND(U68*(1+Assumptions!D88),0) -> 351 | W68: =ROUND(V68*(1+Assumptions!D88),0) -> 362 | X68: =ROUND(W68*(1+Assumptions!D88),0) -> 373 | Y68: =ROUND(X68*(1+Assumptions!D88),0) -> 384 | Z68: =ROUND(Y68*(1+Assumptions!D88),0) -> 396
B69: Insurance / Legal / Misc | C69: =Assumptions!C89 -> 150 | D69: =ROUND(C69*(1+Assumptions!D89),0) -> 150 | E69: =ROUND(D69*(1+Assumptions!D89),0) -> 150 | F69: =ROUND(E69*(1+Assumptions!D89),0) -> 150 | G69: =ROUND(F69*(1+Assumptions!D89),0) -> 150 | H69: =ROUND(G69*(1+Assumptions!D89),0) -> 150 | I69: =ROUND(H69*(1+Assumptions!D89),0) -> 150 | J69: =ROUND(I69*(1+Assumptions!D89),0) -> 150 | K69: =ROUND(J69*(1+Assumptions!D89),0) -> 150 | L69: =ROUND(K69*(1+Assumptions!D89),0) -> 150 | M69: =ROUND(L69*(1+Assumptions!D89),0) -> 150 | N69: =ROUND(M69*(1+Assumptions!D89),0) -> 150 | O69: =ROUND(N69*(1+Assumptions!D89),0) -> 150 | P69: =ROUND(O69*(1+Assumptions!D89),0) -> 150 | Q69: =ROUND(P69*(1+Assumptions!D89),0) -> 150 | R69: =ROUND(Q69*(1+Assumptions!D89),0) -> 150 | S69: =ROUND(R69*(1+Assumptions!D89),0) -> 150 | T69: =ROUND(S69*(1+Assumptions!D89),0) -> 150 | U69: =ROUND(T69*(1+Assumptions!D89),0) -> 150 | V69: =ROUND(U69*(1+Assumptions!D89),0) -> 150 | W69: =ROUND(V69*(1+Assumptions!D89),0) -> 150 | X69: =ROUND(W69*(1+Assumptions!D89),0) -> 150 | Y69: =ROUND(X69*(1+Assumptions!D89),0) -> 150 | Z69: =ROUND(Y69*(1+Assumptions!D89),0) -> 150
B70: TOTAL OPERATING EXPENSES | C70: =SUM(C64:C69) -> 1592.9555 | D70: =SUM(D64:D69) -> 1691.4254 | E70: =SUM(E64:E69) -> 1796.5074 | F70: =SUM(F64:F69) -> 1908.2588 | G70: =SUM(G64:G69) -> 2032.5044 | H70: =SUM(H64:H69) -> 2167.0844 | I70: =SUM(I64:I69) -> 2307.9056 | J70: =SUM(J64:J69) -> 2466.4642 | ... Z70: =SUM(Z64:Z69) -> 7758.8255
B72: PROFIT & LOSS
B73: EBITDA (Gross Profit - OpEx) | C73: =C60-C70 -> 3091.7145 | D73: =D60-D70 -> 3501.5446 | E73: =E60-E70 -> 3963.2226 | F73: =F60-F70 -> 4451.2312 | G73: =G60-G70 -> 5026.7056 | H73: =H60-H70 -> 5655.3256 | I73: =I60-I70 -> 6293.6944 | J73: =J60-J70 -> 7066.7758 | ... Z73: =Z60-Z70 -> 36902.285
B74: EBITDA Margin % | C74: =IF(C52>0,C73/C52,0) -> 0.5111818 | D74: =IF(D52>0,D73/D52,0) -> 0.52395037 | E74: =IF(E52>0,E73/E52,0) -> 0.53646012 | F74: =IF(F52>0,F73/F52,0) -> 0.54733927 | G74: =IF(G52>0,G73/G52,0) -> 0.55869604 | H74: =IF(H52>0,H73/H52,0) -> 0.56883693 | I74: =IF(I52>0,I73/I52,0) -> 0.57678932 | J74: =IF(J52>0,J73/J52,0) -> 0.5859079 | ... Z74: =IF(Z52>0,Z73/Z52,0) -> 0.66920935
B75: Tax (on positive EBITDA) | C75: =IF(C73>0,C73*Assumptions!C92,0) -> 649.26004 | D75: =IF(D73>0,D73*Assumptions!C92,0) -> 735.32437 | E75: =IF(E73>0,E73*Assumptions!C92,0) -> 832.27674 | F75: =IF(F73>0,F73*Assumptions!C92,0) -> 934.75855 | G75: =IF(G73>0,G73*Assumptions!C92,0) -> 1055.6082 | H75: =IF(H73>0,H73*Assumptions!C92,0) -> 1187.6184 | I75: =IF(I73>0,I73*Assumptions!C92,0) -> 1321.6758 | J75: =IF(J73>0,J73*Assumptions!C92,0) -> 1484.0229 | K75: =IF(K73>0,K73*Assumptions!C92,0) -> 1657.1075 | L75: =IF(L73>0,L73*Assumptions!C92,0) -> 1858.9735 | M75: =IF(M73>0,M73*Assumptions!C92,0) -> 2059.3363 | N75: =IF(N73>0,N73*Assumptions!C92,0) -> 2288.6897 | O75: =IF(O73>0,O73*Assumptions!C92,0) -> 2538.9821 | P75: =IF(P73>0,P73*Assumptions!C92,0) -> 2808.7069 | Q75: =IF(Q73>0,Q73*Assumptions!C92,0) -> 3119.4969 | R75: =IF(R73>0,R73*Assumptions!C92,0) -> 3454.0157 | S75: =IF(S73>0,S73*Assumptions!C92,0) -> 3830.6177 | T75: =IF(T73>0,T73*Assumptions!C92,0) -> 4236.5352 | U75: =IF(U73>0,U73*Assumptions!C92,0) -> 4695.4786 | V75: =IF(V73>0,V73*Assumptions!C92,0) -> 5189.4751 | W75: =IF(W73>0,W73*Assumptions!C92,0) -> 5741.0756 | X75: =IF(X73>0,X73*Assumptions!C92,0) -> 6348.9202 | Y75: =IF(Y73>0,Y73*Assumptions!C92,0) -> 7021.1842 | Z75: =IF(Z73>0,Z73*Assumptions!C92,0) -> 7749.4798
B76: NET INCOME | C76: =C73-C75 -> 2442.4544 | D76: =D73-D75 -> 2766.2202 | E76: =E73-E75 -> 3130.9458 | F76: =F73-F75 -> 3516.4726 | G76: =G73-G75 -> 3971.0974 | H76: =H73-H75 -> 4467.7072 | I76: =I73-I75 -> 4972.0185 | J76: =J73-J75 -> 5582.7529 | ... Z76: =Z73-Z75 -> 29152.805
B77: Cumulative Net Income | C77: =C76 -> 2442.4544 | D77: =C77+D76 -> 5208.6747 | E77: =D77+E76 -> 8339.6205 | F77: =E77+F76 -> 11856.093 | G77: =F77+G76 -> 15827.191 | H77: =G77+H76 -> 20294.898 | I77: =H77+I76 -> 25266.916 | J77: =I77+J76 -> 30849.669 | K77: =J77+K76 -> 37083.55 | ... Z77: =Y77+Z76 -> 273861.48
B79: KEY METRICS
B80: Customer Acquisition Cost (CAC) | C80: =IF(C9>0,C65/C9,0) -> 3.2258065 | D80: =IF(D9>0,D65/D9,0) -> 3.1065089 | E80: =IF(E9>0,E65/E9,0) -> 2.9945652 | F80: =IF(F9>0,F65/F9,0) -> 2.895 | G80: =IF(G9>0,G65/G9,0) -> 2.7889908 | H80: =IF(H9>0,H65/H9,0) -> 2.6806723 | I80: =IF(I9>0,I65/I9,0) -> 2.5868726 | J80: =IF(J9>0,J65/J9,0) -> 2.4876325 | ... Z80: =IF(Z9>0,Z65/Z9,0) -> 1.3307359
B81: Avg Revenue Per Charm Sold | C81: =IF(C9>0,C52/C9,0) -> 39.020452 | D81: =IF(D9>0,D52/D9,0) -> 39.544201 | E81: =IF(E9>0,E52/E9,0) -> 40.150707 | F81: =IF(F9>0,F52/F9,0) -> 40.66245 | G81: =IF(G9>0,G52/G9,0) -> 41.271606 | H81: =IF(H9>0,H52/H9,0) -> 41.772731 | I81: =IF(I9>0,I52/I9,0) -> 42.12973 | J81: =IF(J9>0,J52/J9,0) -> 42.619223 | ... Z81: =IF(Z9>0,Z52/Z9,0) -> 47.742952
B82: All-in Cost Per Charm (COGS+OpEx) | C82: =IF(C9>0,(C59+C70)/C9,0) -> 19.073907 | D82: =IF(D9>0,(D59+D70)/D9,0) -> 18.825002 | E82: =IF(E9>0,(E59+E70)/E9,0) -> 18.611454 | F82: =IF(F9>0,(F59+F70)/F9,0) -> 18.406294 | G82: =IF(G9>0,(G59+G70)/G9,0) -> 18.213323 | H82: =IF(H9>0,(H59+H70)/H9,0) -> 18.010859 | I82: =IF(I9>0,(I59+I70)/I9,0) -> 17.829752 | J82: =IF(J9>0,(J59+J70)/J9,0) -> 17.648283 | ... Z82: =IF(Z9>0,(Z59+Z70)/Z9,0) -> 15.792922
B83: Infra Cost Per Active Charm (Monthly) | C83: =IF(C11>0,C43/C11,0) -> 0.18983801 | D83: =IF(D11>0,D43/D11,0) -> 0.09134274 | E83: =IF(E11>0,E43/E11,0) -> 0.058479803 | F83: =IF(F11>0,F43/F11,0) -> 0.042220295 | G83: =IF(G11>0,G43/G11,0) -> 0.032509909 | H83: =IF(H11>0,H43/H11,0) -> 0.026055642 | I83: =IF(I11>0,I43/I11,0) -> 0.021462181 | J83: =IF(J11>0,J43/J11,0) -> 0.018060854 | ... Z83: =IF(Z11>0,Z43/Z11,0) -> 0.0033406919
B84: Total Storage (GB — Azure + R2 combined) | C84: =C15*2 -> 9.28 | D84: =D15*2 -> 19.4 | E84: =E15*2 -> 30.42 | F84: =F15*2 -> 42.4 | G84: =G15*2 -> 55.46 | H84: =H15*2 -> 69.72 | I84: =I15*2 -> 85.24 | J84: =J15*2 -> 102.2 | ... Z84: =Z15*2 -> 721.24
B85: Monthly Profitable? (EBITDA > 0) | C85: =IF(C73>0,"YES","NO") -> YES | D85: =IF(D73>0,"YES","NO") -> YES | E85: =IF(E73>0,"YES","NO") -> YES | F85: =IF(F73>0,"YES","NO") -> YES | G85: =IF(G73>0,"YES","NO") -> YES | H85: =IF(H73>0,"YES","NO") -> YES | I85: =IF(I73>0,"YES","NO") -> YES | J85: =IF(J73>0,"YES","NO") -> YES | ... Z85: =IF(Z73>0,"YES","NO") -> YES
B87: RETURNS & REPLACEMENTS
B88: Returned Charms (units) | C88: =ROUND(C9*Assumptions!C96,0) -> 9 | D88: =ROUND(D9*Assumptions!C96,0) -> 10 | E88: =ROUND(E9*Assumptions!C96,0) -> 11 | F88: =ROUND(F9*Assumptions!C96,0) -> 12 | G88: =ROUND(G9*Assumptions!C96,0) -> 13 | H88: =ROUND(H9*Assumptions!C96,0) -> 14 | I88: =ROUND(I9*Assumptions!C96,0) -> 16 | J88: =ROUND(J9*Assumptions!C96,0) -> 17 | K88: =ROUND(K9*Assumptions!C96,0) -> 19 | L88: =ROUND(L9*Assumptions!C96,0) -> 20 | M88: =ROUND(M9*Assumptions!C96,0) -> 22 | N88: =ROUND(N9*Assumptions!C96,0) -> 24 | O88: =ROUND(O9*Assumptions!C96,0) -> 26 | P88: =ROUND(P9*Assumptions!C96,0) -> 29 | Q88: =ROUND(Q9*Assumptions!C96,0) -> 31 | R88: =ROUND(R9*Assumptions!C96,0) -> 34 | S88: =ROUND(S9*Assumptions!C96,0) -> 37 | T88: =ROUND(T9*Assumptions!C96,0) -> 41 | U88: =ROUND(U9*Assumptions!C96,0) -> 44 | V88: =ROUND(V9*Assumptions!C96,0) -> 49 | W88: =ROUND(W9*Assumptions!C96,0) -> 53 | X88: =ROUND(X9*Assumptions!C96,0) -> 58 | Y88: =ROUND(Y9*Assumptions!C96,0) -> 63 | Z88: =ROUND(Z9*Assumptions!C96,0) -> 69
B89: Pre-Claim Returns (restockable) | C89: =ROUND(C88*Assumptions!C97,0) -> 5 | D89: =ROUND(D88*Assumptions!C97,0) -> 6 | E89: =ROUND(E88*Assumptions!C97,0) -> 7 | F89: =ROUND(F88*Assumptions!C97,0) -> 7 | G89: =ROUND(G88*Assumptions!C97,0) -> 8 | H89: =ROUND(H88*Assumptions!C97,0) -> 8 | I89: =ROUND(I88*Assumptions!C97,0) -> 10 | J89: =ROUND(J88*Assumptions!C97,0) -> 10 | K89: =ROUND(K88*Assumptions!C97,0) -> 11 | L89: =ROUND(L88*Assumptions!C97,0) -> 12 | M89: =ROUND(M88*Assumptions!C97,0) -> 13 | N89: =ROUND(N88*Assumptions!C97,0) -> 14 | O89: =ROUND(O88*Assumptions!C97,0) -> 16 | P89: =ROUND(P88*Assumptions!C97,0) -> 17 | Q89: =ROUND(Q88*Assumptions!C97,0) -> 19 | R89: =ROUND(R88*Assumptions!C97,0) -> 20 | S89: =ROUND(S88*Assumptions!C97,0) -> 22 | T89: =ROUND(T88*Assumptions!C97,0) -> 25 | U89: =ROUND(U88*Assumptions!C97,0) -> 26 | V89: =ROUND(V88*Assumptions!C97,0) -> 29 | W89: =ROUND(W88*Assumptions!C97,0) -> 32 | X89: =ROUND(X88*Assumptions!C97,0) -> 35 | Y89: =ROUND(Y88*Assumptions!C97,0) -> 38 | Z89: =ROUND(Z88*Assumptions!C97,0) -> 41
B90: Post-Claim Returns (dead stock) | C90: =C88-C89 -> 4 | D90: =D88-D89 -> 4 | E90: =E88-E89 -> 4 | F90: =F88-F89 -> 5 | G90: =G88-G89 -> 5 | H90: =H88-H89 -> 6 | I90: =I88-I89 -> 6 | J90: =J88-J89 -> 7 | ... Z90: =Z88-Z89 -> 28
B91: Replacement Charms Shipped (defects) | C91: =ROUND(C9*Assumptions!C101,0) -> 5 | D91: =ROUND(D9*Assumptions!C101,0) -> 5 | E91: =ROUND(E9*Assumptions!C101,0) -> 6 | F91: =ROUND(F9*Assumptions!C101,0) -> 6 | G91: =ROUND(G9*Assumptions!C101,0) -> 7 | H91: =ROUND(H9*Assumptions!C101,0) -> 7 | I91: =ROUND(I9*Assumptions!C101,0) -> 8 | J91: =ROUND(J9*Assumptions!C101,0) -> 8 | K91: =ROUND(K9*Assumptions!C101,0) -> 9 | L91: =ROUND(L9*Assumptions!C101,0) -> 10 | M91: =ROUND(M9*Assumptions!C101,0) -> 11 | N91: =ROUND(N9*Assumptions!C101,0) -> 12 | O91: =ROUND(O9*Assumptions!C101,0) -> 13 | P91: =ROUND(P9*Assumptions!C101,0) -> 14 | Q91: =ROUND(Q9*Assumptions!C101,0) -> 16 | R91: =ROUND(R9*Assumptions!C101,0) -> 17 | S91: =ROUND(S9*Assumptions!C101,0) -> 19 | T91: =ROUND(T9*Assumptions!C101,0) -> 20 | U91: =ROUND(U9*Assumptions!C101,0) -> 22 | V91: =ROUND(V9*Assumptions!C101,0) -> 24 | W91: =ROUND(W9*Assumptions!C101,0) -> 27 | X91: =ROUND(X9*Assumptions!C101,0) -> 29 | Y91: =ROUND(Y9*Assumptions!C101,0) -> 32 | Z91: =ROUND(Z9*Assumptions!C101,0) -> 35
B93: RETURN & REPLACEMENT COSTS
B94: Refund Amount (returned units x avg price) | C94: =IF(C9>0, C88*(C52/C9), 0) -> 351.18406 | D94: =IF(D9>0, D88*(D52/D9), 0) -> 395.44201 | E94: =IF(E9>0, E88*(E52/E9), 0) -> 441.65777 | F94: =IF(F9>0, F88*(F52/F9), 0) -> 487.9494 | G94: =IF(G9>0, G88*(G52/G9), 0) -> 536.53087 | H94: =IF(H9>0, H88*(H52/H9), 0) -> 584.81824 | I94: =IF(I9>0, I88*(I52/I9), 0) -> 674.07568 | J94: =IF(J9>0, J88*(J52/J9), 0) -> 724.52678 | ... Z94: =IF(Z9>0, Z88*(Z52/Z9), 0) -> 3294.2637
B95: Return Shipping Cost | C95: =C88*Assumptions!C99 -> 45 | D95: =D88*Assumptions!C99 -> 50 | E95: =E88*Assumptions!C99 -> 55 | F95: =F88*Assumptions!C99 -> 60 | G95: =G88*Assumptions!C99 -> 65 | H95: =H88*Assumptions!C99 -> 70 | I95: =I88*Assumptions!C99 -> 80 | J95: =J88*Assumptions!C99 -> 85 | K95: =K88*Assumptions!C99 -> 95 | L95: =L88*Assumptions!C99 -> 100 | M95: =M88*Assumptions!C99 -> 110 | N95: =N88*Assumptions!C99 -> 120 | O95: =O88*Assumptions!C99 -> 130 | P95: =P88*Assumptions!C99 -> 145 | Q95: =Q88*Assumptions!C99 -> 155 | R95: =R88*Assumptions!C99 -> 170 | S95: =S88*Assumptions!C99 -> 185 | T95: =T88*Assumptions!C99 -> 205 | U95: =U88*Assumptions!C99 -> 220 | V95: =V88*Assumptions!C99 -> 245 | W95: =W88*Assumptions!C99 -> 265 | X95: =X88*Assumptions!C99 -> 290 | Y95: =Y88*Assumptions!C99 -> 315 | Z95: =Z88*Assumptions!C99 -> 345
B96: Return Processing / Handling | C96: =C88*Assumptions!C100 -> 18 | D96: =D88*Assumptions!C100 -> 20 | E96: =E88*Assumptions!C100 -> 22 | F96: =F88*Assumptions!C100 -> 24 | G96: =G88*Assumptions!C100 -> 26 | H96: =H88*Assumptions!C100 -> 28 | I96: =I88*Assumptions!C100 -> 32 | J96: =J88*Assumptions!C100 -> 34 | K96: =K88*Assumptions!C100 -> 38 | L96: =L88*Assumptions!C100 -> 40 | M96: =M88*Assumptions!C100 -> 44 | N96: =N88*Assumptions!C100 -> 48 | O96: =O88*Assumptions!C100 -> 52 | P96: =P88*Assumptions!C100 -> 58 | Q96: =Q88*Assumptions!C100 -> 62 | R96: =R88*Assumptions!C100 -> 68 | S96: =S88*Assumptions!C100 -> 74 | T96: =T88*Assumptions!C100 -> 82 | U96: =U88*Assumptions!C100 -> 88 | V96: =V88*Assumptions!C100 -> 98 | W96: =W88*Assumptions!C100 -> 106 | X96: =X88*Assumptions!C100 -> 116 | Y96: =Y88*Assumptions!C100 -> 126 | Z96: =Z88*Assumptions!C100 -> 138
B97: COGS Lost — Post-Claim Returns (dead stock) | C97: =IF(C9>0, C90*(C59/C9), 0) -> 35.187097 | D97: =IF(D9>0, D90*(D59/D9), 0) -> 35.266272 | E97: =IF(E9>0, E90*(E59/E9), 0) -> 35.391304 | F97: =IF(F9>0, F90*(F59/F9), 0) -> 44.325 | G97: =IF(G9>0, G90*(G59/G9), 0) -> 44.449541 | H97: =IF(H9>0, H90*(H59/H9), 0) -> 53.432773 | I97: =IF(I9>0, I90*(I59/I9), 0) -> 53.513514 | J97: =IF(J9>0, J90*(J59/J9), 0) -> 62.530035 | ... Z97: =IF(Z9>0, Z90*(Z59/Z9), 0) -> 254.10909
B98: COGS Salvaged — Pre-Claim Returns (restocked) | C98: =IF(C9>0, -C89*(C59/C9)*Assumptions!C98, 0) -> -35.187097 | D98: =IF(D9>0, -D89*(D59/D9)*Assumptions!C98, 0) -> -42.319527 | E98: =IF(E9>0, -E89*(E59/E9)*Assumptions!C98, 0) -> -49.547826 | F98: =IF(F9>0, -F89*(F59/F9)*Assumptions!C98, 0) -> -49.644 | G98: =IF(G9>0, -G89*(G59/G9)*Assumptions!C98, 0) -> -56.895413 | H98: =IF(H9>0, -H89*(H59/H9)*Assumptions!C98, 0) -> -56.994958 | I98: =IF(I9>0, -I89*(I59/I9)*Assumptions!C98, 0) -> -71.351351 | J98: =IF(J9>0, -J89*(J59/J9)*Assumptions!C98, 0) -> -71.462898 | K98: =IF(K9>0, -K89*(K59/K9)*Assumptions!C98, 0) -> -78.730097 | L98: =IF(L9>0, -L89*(L59/L9)*Assumptions!C98, 0) -> -86.059172 | M98: =IF(M9>0, -M89*(M59/M9)*Assumptions!C98, 0) -> -93.317391 | N98: =IF(N9>0, -N89*(N59/N9)*Assumptions!C98, 0) -> -100.63242 | O98: =IF(O9>0, -O89*(O59/O9)*Assumptions!C98, 0) -> -115.18535 | P98: =IF(P9>0, -P89*(P59/P9)*Assumptions!C98, 0) -> -122.48571 | Q98: =IF(Q9>0, -Q89*(Q59/Q9)*Assumptions!C98, 0) -> -137.04846 | R98: =IF(R9>0, -R89*(R59/R9)*Assumptions!C98, 0) -> -144.3662 | S98: =IF(S9>0, -S89*(S59/S9)*Assumptions!C98, 0) -> -158.95266 | T98: =IF(T9>0, -T89*(T59/T9)*Assumptions!C98, 0) -> -180.78171 | U98: =IF(U9>0, -U89*(U59/U9)*Assumptions!C98, 0) -> -188.15439 | V98: =IF(V9>0, -V89*(V59/V9)*Assumptions!C98, 0) -> -210.00445 | W98: =IF(W9>0, -W89*(W59/W9)*Assumptions!C98, 0) -> -231.93484 | X98: =IF(X9>0, -X89*(X59/X9)*Assumptions!C98, 0) -> -253.79524 | Y98: =IF(Y9>0, -Y89*(Y59/Y9)*Assumptions!C98, 0) -> -275.77143 | Z98: =IF(Z9>0, -Z89*(Z59/Z9)*Assumptions!C98, 0) -> -297.67065
B99: Replacement COGS (defect units x COGS) | C99: =IF(C9>0, C91*(C59/C9)*Assumptions!C103, 0) -> 43.983871 | D99: =IF(D9>0, D91*(D59/D9)*Assumptions!C103, 0) -> 44.08284 | E99: =IF(E9>0, E91*(E59/E9)*Assumptions!C103, 0) -> 53.086957 | F99: =IF(F9>0, F91*(F59/F9)*Assumptions!C103, 0) -> 53.19 | G99: =IF(G9>0, G91*(G59/G9)*Assumptions!C103, 0) -> 62.229358 | H99: =IF(H9>0, H91*(H59/H9)*Assumptions!C103, 0) -> 62.338235 | I99: =IF(I9>0, I91*(I59/I9)*Assumptions!C103, 0) -> 71.351351 | J99: =IF(J9>0, J91*(J59/J9)*Assumptions!C103, 0) -> 71.462898 | K99: =IF(K9>0, K91*(K59/K9)*Assumptions!C103, 0) -> 80.519417 | L99: =IF(L9>0, L91*(L59/L9)*Assumptions!C103, 0) -> 89.64497 | M99: =IF(M9>0, M91*(M59/M9)*Assumptions!C103, 0) -> 98.701087 | N99: =IF(N9>0, N91*(N59/N9)*Assumptions!C103, 0) -> 107.82045 | O99: =IF(O9>0, O91*(O59/O9)*Assumptions!C103, 0) -> 116.98513 | P99: =IF(P9>0, P91*(P59/P9)*Assumptions!C103, 0) -> 126.08824 | Q99: =IF(Q9>0, Q91*(Q59/Q9)*Assumptions!C103, 0) -> 144.26154 | R99: =IF(R9>0, R91*(R59/R9)*Assumptions!C103, 0) -> 153.38908 | S99: =IF(S9>0, S91*(S59/S9)*Assumptions!C103, 0) -> 171.59662 | T99: =IF(T9>0, T91*(T59/T9)*Assumptions!C103, 0) -> 180.78171 | U99: =IF(U9>0, U91*(U59/U9)*Assumptions!C103, 0) -> 199.00945 | V99: =IF(V9>0, V91*(V59/V9)*Assumptions!C103, 0) -> 217.24598 | W99: =IF(W9>0, W91*(W59/W9)*Assumptions!C103, 0) -> 244.61878 | X99: =IF(X9>0, X91*(X59/X9)*Assumptions!C103, 0) -> 262.85936 | Y99: =IF(Y9>0, Y91*(Y59/Y9)*Assumptions!C103, 0) -> 290.28571 | Z99: =IF(Z9>0, Z91*(Z59/Z9)*Assumptions!C103, 0) -> 317.63636
B100: Replacement Shipping | C100: =C91*Assumptions!C102 -> 17.5 | D100: =D91*Assumptions!C102 -> 17.5 | E100: =E91*Assumptions!C102 -> 21 | F100: =F91*Assumptions!C102 -> 21 | G100: =G91*Assumptions!C102 -> 24.5 | H100: =H91*Assumptions!C102 -> 24.5 | I100: =I91*Assumptions!C102 -> 28 | J100: =J91*Assumptions!C102 -> 28 | K100: =K91*Assumptions!C102 -> 31.5 | L100: =L91*Assumptions!C102 -> 35 | M100: =M91*Assumptions!C102 -> 38.5 | N100: =N91*Assumptions!C102 -> 42 | O100: =O91*Assumptions!C102 -> 45.5 | P100: =P91*Assumptions!C102 -> 49 | Q100: =Q91*Assumptions!C102 -> 56 | R100: =R91*Assumptions!C102 -> 59.5 | S100: =S91*Assumptions!C102 -> 66.5 | T100: =T91*Assumptions!C102 -> 70 | U100: =U91*Assumptions!C102 -> 77 | V100: =V91*Assumptions!C102 -> 84 | W100: =W91*Assumptions!C102 -> 94.5 | X100: =X91*Assumptions!C102 -> 101.5 | Y100: =Y91*Assumptions!C102 -> 112 | Z100: =Z91*Assumptions!C102 -> 122.5
B101: TOTAL RETURNS & REPLACEMENT IMPACT | C101: =C94+C95+C96+C97+C98+C99+C100 -> 475.66794 | D101: =D94+D95+D96+D97+D98+D99+D100 -> 519.9716 | E101: =E94+E95+E96+E97+E98+E99+E100 -> 578.58821 | F101: =F94+F95+F96+F97+F98+F99+F100 -> 640.8204 | G101: =G94+G95+G96+G97+G98+G99+G100 -> 701.81436 | H101: =H94+H95+H96+H97+H98+H99+H100 -> 766.09429 | I101: =I94+I95+I96+I97+I98+I99+I100 -> 867.58919 | J101: =J94+J95+J96+J97+J98+J99+J100 -> 934.05682 | ... Z101: =Z94+Z95+Z96+Z97+Z98+Z99+Z100 -> 4173.8385
B103: ADJUSTED P&L (After Returns & Replacements)
B104: Net Revenue (gross - refunds) | C104: =C52-C94 -> 5696.9859 | D104: =D52-D94 -> 6287.528 | E104: =E52-E94 -> 6946.0722 | F104: =F52-F94 -> 7644.5406 | G104: =G52-G94 -> 8460.6791 | H104: =H52-H94 -> 9357.0918 | I104: =I52-I94 -> 10237.524 | J104: =J52-J94 -> 11336.713 | ... Z104: =Z52-Z94 -> 51848.846
B105: Adjusted COGS (incl. dead stock + replacements) | C105: =C59+C97+C98+C99 -> 1407.4839 | D105: =D59+D97+D98+D99 -> 1527.0296 | E105: =E59+E97+E98+E99 -> 1666.9304 | F105: =F59+F97+F98+F99 -> 1820.871 | G105: =G59+G97+G98+G99 -> 1987.7835 | H105: =H59+H97+H98+H99 -> 2178.2761 | I105: =I59+I97+I98+I99 -> 2363.5135 | J105: =J59+J97+J98+J99 -> 2590.53 | ... Z105: =Z59+Z97+Z98+Z99 -> 10756.075
B106: Return & Replacement Overhead (shipping + processing) | C106: =C95+C96+C100 -> 80.5 | D106: =D95+D96+D100 -> 87.5 | E106: =E95+E96+E100 -> 98 | F106: =F95+F96+F100 -> 105 | G106: =G95+G96+G100 -> 115.5 | H106: =H95+H96+H100 -> 122.5 | I106: =I95+I96+I100 -> 140 | J106: =J95+J96+J100 -> 147 | ... Z106: =Z95+Z96+Z100 -> 605.5
B107: Adjusted Gross Profit | C107: =C104-C105-C106 -> 4209.0021 | D107: =D104-D105-D106 -> 4672.9984 | E107: =E104-E105-E106 -> 5181.1418 | F107: =F104-F105-F106 -> 5718.6696 | G107: =G104-G105-G106 -> 6357.3956 | H107: =H104-H105-H106 -> 7056.3157 | I107: =I104-I105-I106 -> 7734.0108 | J107: =J104-J105-J106 -> 8599.1832 | ... Z107: =Z104-Z105-Z106 -> 40487.271
B108: Adjusted Gross Margin % | C108: =IF(C104>0,C107/C104,0) -> 0.73881209 | D108: =IF(D104>0,D107/D104,0) -> 0.74321711 | E108: =IF(E104>0,E107/E104,0) -> 0.74590958 | F108: =IF(F104>0,F107/F104,0) -> 0.74807237 | G108: =IF(G104>0,G107/G104,0) -> 0.75140489 | H108: =IF(H104>0,H107/H104,0) -> 0.75411419 | I108: =IF(I104>0,I107/I104,0) -> 0.75545714 | J108: =IF(J104>0,J107/J104,0) -> 0.75852525 | ... Z108: =IF(Z104>0,Z107/Z104,0) -> 0.78087121
B109: Adjusted EBITDA | C109: =C107-C70 -> 2616.0465 | D109: =D107-D70 -> 2981.573 | E109: =E107-E70 -> 3384.6343 | F109: =F107-F70 -> 3810.4108 | G109: =G107-G70 -> 4324.8913 | H109: =H107-H70 -> 4889.2313 | I109: =I107-I70 -> 5426.1052 | J109: =J107-J70 -> 6132.719 | ... Z109: =Z107-Z70 -> 32728.446
B110: Adjusted EBITDA Margin % | C110: =IF(C104>0,C109/C104,0) -> 0.45919835 | D110: =IF(D104>0,D109/D104,0) -> 0.47420433 | E110: =IF(E104>0,E109/E104,0) -> 0.48727313 | F110: =IF(F104>0,F109/F104,0) -> 0.49844863 | G110: =IF(G104>0,G109/G104,0) -> 0.51117543 | H110: =IF(H104>0,H109/H104,0) -> 0.52251612 | I110: =IF(I104>0,I109/I104,0) -> 0.53002122 | J110: =IF(J104>0,J109/J104,0) -> 0.54096094 | ... Z110: =IF(Z104>0,Z109/Z104,0) -> 0.63122805
B111: Adjusted Net Income | C111: =C109-IF(C109>0,C109*Assumptions!C92,0) -> 2066.6767 | D111: =D109-IF(D109>0,D109*Assumptions!C92,0) -> 2355.4427 | E111: =E109-IF(E109>0,E109*Assumptions!C92,0) -> 2673.8611 | F111: =F109-IF(F109>0,F109*Assumptions!C92,0) -> 3010.2245 | G111: =G109-IF(G109>0,G109*Assumptions!C92,0) -> 3416.6641 | H111: =H109-IF(H109>0,H109*Assumptions!C92,0) -> 3862.4927 | I111: =I109-IF(I109>0,I109*Assumptions!C92,0) -> 4286.6231 | J111: =J109-IF(J109>0,J109*Assumptions!C92,0) -> 4844.848 | K111: =K109-IF(K109>0,K109*Assumptions!C92,0) -> 5400.3526 | L111: =L109-IF(L109>0,L109*Assumptions!C92,0) -> 6108.1307 | M111: =M109-IF(M109>0,M109*Assumptions!C92,0) -> 6765.3482 | N111: =N109-IF(N109>0,N109*Assumptions!C92,0) -> 7528.9918 | O111: =O109-IF(O109>0,O109*Assumptions!C92,0) -> 8383.618 | P111: =P109-IF(P109>0,P109*Assumptions!C92,0) -> 9250.5602 | Q111: =Q109-IF(Q109>0,Q109*Assumptions!C92,0) -> 10320.816 | R111: =R109-IF(R109>0,R109*Assumptions!C92,0) -> 11429.699 | S111: =S109-IF(S109>0,S109*Assumptions!C92,0) -> 12697.56 | T111: =T109-IF(T109>0,T109*Assumptions!C92,0) -> 14048.721 | U111: =U109-IF(U109>0,U109*Assumptions!C92,0) -> 15609.865 | V111: =V109-IF(V109>0,V109*Assumptions!C92,0) -> 17229.535 | W111: =W109-IF(W109>0,W109*Assumptions!C92,0) -> 19102.88 | X111: =X109-IF(X109>0,X109*Assumptions!C92,0) -> 21147.907 | Y111: =Y109-IF(Y109>0,Y109*Assumptions!C92,0) -> 23421.357 | Z111: =Z109-IF(Z109>0,Z109*Assumptions!C92,0) -> 25855.472
B112: Net Active Charms (adjusted for returns) | C112: =C11-C90 -> 128 | D112: =C112+(D9*Assumptions!C34)-D90 -> 267.65 | E112: =D112+(E9*Assumptions!C34)-E90 -> 420.05 | F112: =E112+(F9*Assumptions!C34)-F90 -> 585.05 | G112: =F112+(G9*Assumptions!C34)-G90 -> 765.35 | H112: =G112+(H9*Assumptions!C34)-H90 -> 961.65 | I112: =H112+(I9*Assumptions!C34)-I90 -> 1175.8 | J112: =I112+(J9*Assumptions!C34)-J90 -> 1409.35 | K112: =J112+(K9*Assumptions!C34)-K90 -> 1664 | L112: =K112+(L9*Assumptions!C34)-L90 -> 1943.3 | M112: =L112+(M9*Assumptions!C34)-M90 -> 2247.1 | N112: =M112+(N9*Assumptions!C34)-N90 -> 2577.95 | O112: =N112+(O9*Assumptions!C34)-O90 -> 2939.4 | P112: =O112+(P9*Assumptions!C34)-P90 -> 3332 | Q112: =P112+(Q9*Assumptions!C34)-Q90 -> 3762 | R112: =Q112+(R9*Assumptions!C34)-R90 -> 4230.8 | S112: =R112+(S9*Assumptions!C34)-S90 -> 4743.65 | T112: =S112+(T9*Assumptions!C34)-T90 -> 5303.95 | U112: =T112+(U9*Assumptions!C34)-U90 -> 5915.8 | V112: =U112+(V9*Assumptions!C34)-V90 -> 6583.45 | W112: =V112+(W9*Assumptions!C34)-W90 -> 7313.85 | X112: =W112+(X9*Assumptions!C34)-X90 -> 8112.8 | Y112: =X112+(Y9*Assumptions!C34)-Y90 -> 8986.25 | Z112: =Y112+(Z9*Assumptions!C34)-Z90 -> 9940
...

Sheet Annual Summary
B1: MemoryCharm — Annual Summary
C3: Year 1 (M1-12) | D3: Year 2 (M13-24) | E3: Total (24 Mo)
B5: Total Charms Sold | C5: =SUM('24-Month Projections'!C9:N9) -> 3122 | D5: =SUM('24-Month Projections'!O9:Z9) -> 8913 | E5: =C5+D5 -> 12035
B6: Cumulative Charms (End) | C6: ='24-Month Projections'!N10 -> 3122 | D6: ='24-Month Projections'!Z10 -> 12035 | E6: =D6 -> 12035
B7: Active Charms (End) | C7: ='24-Month Projections'!N11 -> 2654 | D7: ='24-Month Projections'!Z11 -> 10230 | E7: =D7 -> 10230
B8: Total Storage (GB, end of period) | C8: ='24-Month Projections'!N15 -> 93.54 | D8: ='24-Month Projections'!Z15 -> 360.62 | E8: =D8 -> 360.62
B10: Total Revenue | C10: =SUM('24-Month Projections'!C52:N52) -> 132013.99 | D10: =SUM('24-Month Projections'!O52:Z52) -> 414546.66 | E10: =C10+D10 -> 546560.65
B11: Charm Revenue | C11: =SUM('24-Month Projections'!C46:N46)+SUM('24-Month Projections'!C47:N47)+SUM('24-Month Projections'!C48:N48) -> 121163.78 | D11: =SUM('24-Month Projections'!O46:Z46)+SUM('24-Month Projections'!O47:Z47)+SUM('24-Month Projections'!O48:Z48) -> 364830.87 | E11: =C11+D11 -> 485994.65
B12: Upsell Revenue | C12: =SUM('24-Month Projections'!C49:N49)+SUM('24-Month Projections'!C50:N50)+SUM('24-Month Projections'!C51:N51) -> 10850.21 | D12: =SUM('24-Month Projections'!O49:Z49)+SUM('24-Month Projections'!O50:Z50)+SUM('24-Month Projections'!O51:Z51) -> 49715.79 | E12: =C12+D12 -> 60566
B14: Total COGS | C14: =SUM('24-Month Projections'!C59:N59) -> 27849.5 | D14: =SUM('24-Month Projections'!O59:Z59) -> 80640.5 | E14: =C14+D14 -> 108490
B15: Gross Profit | C15: =SUM('24-Month Projections'!C60:N60) -> 104164.49 | D15: =SUM('24-Month Projections'!O60:Z60) -> 333906.16 | E15: =C15+D15 -> 438070.65
B16: Gross Margin % | C16: =IF(C10>0,C15/C10,0) -> 0.7890413 | D16: =IF(D10>0,D15/D10,0) -> 0.80547304 | E16: =IF(E10>0,E15/E10,0) -> 0.80150419
B18: Total Operating Expenses | C18: =SUM('24-Month Projections'!C70:N70) -> 27666.147 | D18: =SUM('24-Month Projections'!O70:Z70) -> 63744.408 | E18: =C18+D18 -> 91410.555
B19: Infrastructure | C19: =SUM('24-Month Projections'!C43:N43) -> 311.74137 | D19: =SUM('24-Month Projections'!O43:Z43) -> 365.05441 | E19: =C19+D19 -> 676.79578
B20: Azure Blob Storage | C20: =SUM('24-Month Projections'!C35:N35) -> 5.7491534 | D20: =SUM('24-Month Projections'!O35:Z35) -> 28.077408 | E20: =C20+D20 -> 33.826562
B21: Cloudflare R2 | C21: =SUM('24-Month Projections'!C39:N39) -> 5.97945 | D21: =SUM('24-Month Projections'!O39:Z39) -> 36.92835 | E21: =C21+D21 -> 42.9078
B22: Azure Table Storage | C22: =SUM('24-Month Projections'!C40:N40) -> 0.012764217 | D22: =SUM('24-Month Projections'!O40:Z40) -> 0.048652211 | E22: =C22+D22 -> 0.061416428
B23: Azure Functions | C23: =SUM('24-Month Projections'!C41:N41) -> 0 | D23: =SUM('24-Month Projections'!O41:Z41) -> 0 | E23: =C23+D23 -> 0
B24: Other Platform | C24: =SUM('24-Month Projections'!C42:N42) -> 300 | D24: =SUM('24-Month Projections'!O42:Z42) -> 300 | E24: =C24+D24 -> 600
B25: Marketing | C25: =SUM('24-Month Projections'!C65:N65) -> 7961 | D25: =SUM('24-Month Projections'!O65:Z65) -> 14309 | E25: =C25+D25 -> 22270
B26: Shipping | C26: =SUM('24-Month Projections'!C66:N66) -> 10927 | D26: =SUM('24-Month Projections'!O66:Z66) -> 31195.5 | E26: =C26+D26 -> 42122.5
B27: Payment Processing | C27: =SUM('24-Month Projections'!C67:N67) -> 3828.4057 | D27: =SUM('24-Month Projections'!O67:Z67) -> 12021.853 | E27: =C27+D27 -> 15850.259
B28: Support + Legal | C28: =SUM('24-Month Projections'!C68:N68)+SUM('24-Month Projections'!C69:N69) -> 4638 | D28: =SUM('24-Month Projections'!O68:Z68)+SUM('24-Month Projections'!O69:Z69) -> 5853 | E28: =C28+D28 -> 10491
B30: EBITDA | C30: =SUM('24-Month Projections'!C73:N73) -> 76498.343 | D30: =SUM('24-Month Projections'!O73:Z73) -> 270161.75 | E30: =C30+D30 -> 346660.1
B31: EBITDA Margin % | C31: =IF(C10>0,C30/C10,0) -> 0.57947149 | D31: =IF(D10>0,D30/D10,0) -> 0.65170409 | E31: =IF(E10>0,E30/E10,0) -> 0.63425732
B32: Tax | C32: =SUM('24-Month Projections'!C75:N75) -> 16064.652 | D32: =SUM('24-Month Projections'!O75:Z75) -> 56733.968 | E32: =C32+D32 -> 72798.62
B33: NET INCOME | C33: =SUM('24-Month Projections'!C76:N76) -> 60433.691 | D33: =SUM('24-Month Projections'!O76:Z76) -> 213427.78 | E33: =C33+D33 -> 273861.48
B35: RETURNS & REPLACEMENTS
B36: Returned Units | C36: =SUM('24-Month Projections'!C88:N88) -> 187 | D36: =SUM('24-Month Projections'!O88:Z88) -> 534 | E36: =C36+D36 -> 721
B37: Replacement Units | C37: =SUM('24-Month Projections'!C91:N91) -> 94 | D37: =SUM('24-Month Projections'!O91:Z91) -> 268 | E37: =C37+D37 -> 362
B38: Total Return & Replacement Cost | C38: =SUM('24-Month Projections'!C101:N101) -> 10270.93 | D38: =SUM('24-Month Projections'!O101:Z101) -> 31556.7 | E38: =C38+D38 -> 41827.63
B39: Margin Erosion % | C39: =IF(C10>0,C38/C10,0) -> 0.07780183 | D39: =IF(D10>0,D38/D10,0) -> 0.076123398 | E39: =IF(E10>0,E38/E10,0) -> 0.0765288
B41: ADJUSTED P&L (After Returns)
B42: Net Revenue | C42: =SUM('24-Month Projections'!C104:N104) -> 124105.32 | D42: =SUM('24-Month Projections'!O104:Z104) -> 389710.74 | E42: =C42+D42 -> 513816.06
B43: Adjusted COGS | C43: =SUM('24-Month Projections'!C105:N105) -> 28573.759 | D43: =SUM('24-Month Projections'!O105:Z105) -> 82685.277 | E43: =C43+D43 -> 111259.04
B44: Adjusted Gross Profit | C44: =SUM('24-Month Projections'!C107:N107) -> 93893.56 | D44: =SUM('24-Month Projections'!O107:Z107) -> 302349.46 | E44: =C44+D44 -> 396243.02
B45: Adjusted Gross Margin % | C45: =IF(C42>0,C44/C42,0) -> 0.75656354 | D45: =IF(D42>0,D44/D42,0) -> 0.77583046 | E45: =IF(E42>0,E44/E42,0) -> 0.7711768
B46: Adjusted EBITDA | C46: =SUM('24-Month Projections'!C109:N109) -> 66227.413 | D46: =SUM('24-Month Projections'!O109:Z109) -> 238605.05 | E46: =C46+D46 -> 304832.46
B47: Adjusted EBITDA Margin % | C47: =IF(C42>0,C46/C42,0) -> 0.53363879 | D47: =IF(D42>0,D46/D42,0) -> 0.61226194 | E47: =IF(E42>0,E46/E42,0) -> 0.59327158
B48: ADJUSTED NET INCOME | C48: =SUM('24-Month Projections'!C111:N111) -> 52319.656 | D48: =SUM('24-Month Projections'!O111:Z111) -> 188497.99 | E48: =C48+D48 -> 240817.65

Sheet Scenario Notes
B1: Scenario Playbook
B2: Copy the workbook, change Assumptions, compare results
B4: Assumption | C4: Conservative | D4: Base Case | E4: Optimistic
B5: 10-Year Charm Price | C5: $24.99 | D5: $29.99 | E5: $34.99
B6: 15-Year Charm Price | C6: $39.99 | D6: $44.99 | E6: $54.99
B7: Perpetual Charm Price | C7: $59.99 | D7: $69.99 | E7: $89.99
B8: Starting 10-Year Units/Mo | C8: 50 | D8: 100 | E8: 200
B9: Starting 15-Year Units/Mo | C9: 20 | D9: 40 | E9: 80
B10: Starting Perpetual Units/Mo | C10: 5 | D10: 15 | E10: 30
B11: MoM Growth (10-Year) | C11: 5% | D11: 8% | E11: 12%
B12: MoM Growth (15-Year) | C12: 6% | D12: 10% | E12: 15%
B13: MoM Growth (Perpetual) | C13: 8% | D13: 12% | E13: 18%
B14: COGS per Charm | C14: $10.00 | D14: $8.50 | E14: $7.00
B15: Avg Content Size (MB) | C15: 20 | D15: 35.9 | E15: 60
... B21: Gift Wrap Attach Rate | C21: 8% | D21: 15% | E21: 25%
B23: HOW TO USE:
B24: 1. Base Case values match the Assumptions sheet defaults
B25: 2. Go to Assumptions sheet and change the yellow cells
B26: 3. Projections and Annual Summary auto-update
B27: 4. File > Save As to create copies for each scenario
B28: 5. Key infrastructure levers: content size, views/charm, video mix %

Sheet Per-Charm Costs
B1: Per-Charm Hosting Cost Breakdown (No Free Tier)
B2: What it costs to host ONE charm — raw service rates, no free tier credits applied
B3: All values linked to Assumptions sheet — change inputs there to update these costs
B5: SINGLE CHARM PROFILE
B6: Metric | C6: Value | D6: Unit
B7: Content size (weighted avg) | C7: =Assumptions!C33 -> 36.1 | D7: MB | F7: From Assumptions: video/image/audio weighted mix
B8: Content size in GB | C8: =C7/1024 -> 0.035253906 | D8: GB
B9: Views per month (first 3 months — novelty) | C9: =Assumptions!C38 -> 8 | D9: views/month
B10: Views per month (after 3 months — long-tail) | C10: =Assumptions!C39 -> 2 | D10: views/month
B11: Blended avg views/month (assuming mostly long-tail) | C11: =ROUND((C9*3+C10*9)/12,1) -> 3.5 | D11: views/month | F11: Year-weighted: 3 months novelty + 9 months long-tail
B12: % of views requiring glyph verification | C12: =Assumptions!C40 -> 0.4
B13: API calls per view (GetCharm + glyph if needed) | C13: =1+C12 -> 1.4 | F13: 1 GetCharm call per view + glyph verify probability
B14: Table reads per view | C14: =Assumptions!C43 -> 3
B15: Table writes per view (glyph attempts + rate-limit log) | C15: =ROUND(C12*2+0.1,1) -> 0.9 | F15: 2 writes per glyph verify + 10% sampled request logging
B17: ONE-TIME SETUP COSTS (per charm — claim through finalize)
B18: Service / Operation | C18: Cost | D18: Calculation | E18: Notes
B19: Azure Functions: Lifecycle API Calls | C19: =(Assumptions!C41/1000000)*Assumptions!C69 + Assumptions!C41*(Assumptions!C71/1000)*(Assumptions!C72/1024)*Assumptions!C70 -> 3e-06 | D19: 5 calls x exec + compute cost | F19: claim + configure + get-upload-urls + finalize + preview
B20: Cloudflare R2: Upload Writes (Class A) | C20: =(2*(1+Assumptions!C35)/1000000)*Assumptions!C56 -> 1.08e-05 | D20: 2 PUT ops x (1+re-upload rate) | F20: PUT blob + list verify; re-uploads during 14-day settling
B21: Azure Blob: Backup Upload Writes | C21: =(2*(1+Assumptions!C35)/10000)*Assumptions!C48 -> 2.4e-05 | D21: 2 ops x (1+re-upload rate) / 10K
B22: Azure Table: Setup Entity Writes | C22: =(Assumptions!C42/10000)*Assumptions!C64 -> 2.88e-07 | D22: 8 writes / 10K x txn rate | F22: charm + user-charm + profile + request log entities
B23: Azure Table: Entity Storage (first month) | C23: =(Assumptions!C65/1024/1024)*Assumptions!C63 -> 8.5830688e-08 | D23: ~2 KB entity / GB x rate
B24: TOTAL ONE-TIME SETUP COST | C24: =SUM(C19:C23) -> 3.8173831e-05
B26: MONTHLY ONGOING COSTS (per charm — storage + playback) | F26: Assumes blended avg views/month from row 11
B27: Service / Operation | C27: $/Month | D27: Calculation | E27: Notes
B28: CLOUDFLARE R2
B29: R2: Storage (content GB x rate) | C29: =C8*Assumptions!C55 -> 0.00052880859 | D29: GB x $0.015/GB/mo
B30: R2: Class B Reads — playback downloads | C30: =(C11/1000000)*Assumptions!C57 -> 1.26e-06 | D30: views/mo / 1M x rate | F30: Every view = 1 GET from R2
B31: R2: Egress / Bandwidth | C31: =C11*C8*Assumptions!C58 -> 0 | D31: $0.00 — zero egress | F31: Cloudflare's key advantage: zero bandwidth cost
B32: R2 SUBTOTAL | C32: =C29+C30+C31 -> 0.00053006859
B34: AZURE BLOB STORAGE — COOL TIER
B35: Azure Blob: Storage (backup mirror — same GB) | C35: =C8*Assumptions!C47 -> 0.00035253906 | D35: GB x $0.01/GB/mo
B36: Azure Blob: Read Ops (fallback — 2% of views) | C36: =(C11*0.02/10000)*Assumptions!C49 -> 7e-08 | D36: 2% fallback reads | F36: Only when R2 is unavailable; client falls back to Azure
B37: Azure Blob: Data Retrieval (cool tier penalty) | C37: =C11*0.02*C8*Assumptions!C50 -> 2.4677734e-05 | D37: 2% fallback x GB x retrieval rate | F37: Cool tier charges per-GB on read; hot tier does not
B38: Azure Blob: Egress (fallback downloads) | C38: =C11*0.02*C8*Assumptions!C51 -> 0.00021469629 | D38: 2% fallback x GB x egress rate | F38: $0.087/GB — only on Azure-direct downloads
B39: Azure Blob SUBTOTAL | C39: =C35+C36+C37+C38 -> 0.00059198309
B41: AZURE TABLE STORAGE
B42: Table: Entity Storage (ongoing) | C42: =(Assumptions!C65/1024/1024)*Assumptions!C63 -> 8.5830688e-08 | D42: ~2 KB entity set / month
B43: Table: Read Transactions (views x reads/view) | C43: =(C11*C14/10000)*Assumptions!C64 -> 3.78e-07 | D43: views x 3 reads / 10K x rate
B44: Table: Write Transactions (glyph + logging) | C44: =(C11*C15/10000)*Assumptions!C64 -> 1.134e-07 | D44: views x writes/view / 10K x rate
B45: Azure Table SUBTOTAL | C45: =C42+C43+C44 -> 5.7723069e-07
B47: AZURE FUNCTIONS (Compute)
B48: Functions: Execution Cost (view + glyph calls) | C48: =(C11*C13/1000000)*Assumptions!C69 -> 9.8e-07 | D48: calls / 1M x $0.20
B49: Functions: Compute GB-seconds | C49: =C11*C13*(Assumptions!C71/1000)*(Assumptions!C72/1024)*Assumptions!C70 -> 1.96e-06 | D49: calls x duration x memory x rate | F49: ~200ms avg x 128MB per invocation
B50: Azure Functions SUBTOTAL | C50: =C48+C49 -> 2.94e-06
B52: ENTRA CIAM (Authentication)
B53: CIAM: Per-MAU cost (1 charm ≈ 0.3 MAU avg) | C53: =0.3*Assumptions!C79 -> 0.00075 | D53: 0.3 MAU x $0.0025/MAU | F53: Not every charm = unique monthly active user
B54: CIAM SUBTOTAL | C54: =C53 -> 0.00075
B56: TOTAL MONTHLY HOSTING COST (per charm) | C56: =C32+C39+C45+C50+C54 -> 0.0018755689
B58: ANNUAL & LIFETIME COST SUMMARY (per charm)
B59: Time Horizon | C59: Hosting Cost | D59: Incl. Setup | E59: Notes
B60: Annual Hosting Cost (monthly x 12) | C60: =C56*12 -> 0.022506827 | D60: =C56*12+C24 -> 0.022545001 | F60: Pure recurring hosting — no COGS, no shipping
B61: Year 1 Total (setup + 12 months hosting) | C61: =C56*12 -> 0.022506827 | D61: =C24+C56*12 -> 0.022545001 | F61: First year is highest — includes one-time setup
B63: LIFETIME HOSTING BY TIER
B64: Tier | C64: Hosting Only | D64: Incl. Setup | E64: As % of Retail Price | F64: Hosting Profit/Loss
B65: 10-Year Charm (120 months hosting) | C65: =C56*120 -> 0.22506827 | D65: =C24+C56*120 -> 0.22510644 | E65: =IF(Assumptions!C6>0,D65/Assumptions!C6,0) -> 0.0075060501 | F65: =Assumptions!C6-D65 -> 29.764894
B66: 15-Year Charm (180 months hosting) | C66: =C56*180 -> 0.3376024 | D66: =C24+C56*180 -> 0.33764058 | E66: =IF(Assumptions!C7>0,D66/Assumptions!C7,0) -> 0.0075047917 | F66: =Assumptions!C7-D66 -> 44.652359
B67: Retail / Perpetual Charm (30-year est = 360 months) | C67: =C56*360 -> 0.67520481 | D67: =C24+C56*360 -> 0.67524298 | E67: =IF(Assumptions!C8>0,D67/Assumptions!C8,0) -> 0.0096477066 | F67: =Assumptions!C8-D67 -> 69.314757
B69: MONTHLY COST — SERVICE BREAKDOWN (%)
B70: Service | C70: $/Month | D70: % of Total | E70: Key Driver
B71: Cloudflare R2 | C71: =C32 -> 0.00053006859 | D71: =IF(C56>0,C32/C56,0) -> 0.2826175 | E71: Storage volume (GB per charm)
B72: Azure Blob (Cool Backup) | C72: =C39 -> 0.00059198309 | D72: =IF(C56>0,C39/C56,0) -> 0.31562854 | E72: Storage + fallback reads
B73: Azure Table Storage | C73: =C45 -> 5.7723069e-07 | D73: =IF(C56>0,C45/C56,0) -> 0.00030776299 | E73: Transaction volume (views x ops)
B74: Azure Functions | C74: =C50 -> 2.94e-06 | D74: =IF(C56>0,C50/C56,0) -> 0.0015675244 | E74: API call volume
B75: Entra CIAM | C75: =C54 -> 0.00075 | D75: =IF(C56>0,C54/C56,0) -> 0.39987867 | E75: Monthly active users
B76: TOTAL | C76: =C56 -> 0.0018755689 | D76: =SUM(D71:D75) -> 1
B78: CONTENT SIZE SENSITIVITY — Monthly Cost at Different Sizes | F78: Holding view rate constant, varying content size
B79: Content Size | C79: R2 Storage | D79: Azure Blob | E79: Functions+Table | F79: Total Monthly | G79: Annual (x12)
B80: 6 MB (audio only) | C80: =(6/1024)*Assumptions!C55 -> 8.7890625e-05 | D80: =(6/1024)*Assumptions!C47 + (C11*0.02/10000)*Assumptions!C49 + C11*0.02*(6/1024)*Assumptions!C50 + C11*0.02*(6/1024)*Assumptions!C51 -> 9.8448906e-05 | E80: =C50+C45 -> 3.5172307e-06 | F80: =C80+D80+E80+C54 -> 0.00093985676 | G80: =F80*12 -> 0.011278281
B81: 15 MB (image gallery) | C81: =(15/1024)*Assumptions!C55 -> 0.00021972656 | D81: =(15/1024)*Assumptions!C47 + (C11*0.02/10000)*Assumptions!C49 + C11*0.02*(15/1024)*Assumptions!C50 + C11*0.02*(15/1024)*Assumptions!C51 -> 0.00024601727 | E81: =C50+C45 -> 3.5172307e-06 | F81: =C81+D81+E81+C54 -> 0.0012192611 | G81: =F81*12 -> 0.014631133
B82: 35.85 MB (weighted avg — base case) | C82: =(35.85/1024)*Assumptions!C55 -> 0.00052514648 | D82: =(35.85/1024)*Assumptions!C47 + (C11*0.02/10000)*Assumptions!C49 + C11*0.02*(35.85/1024)*Assumptions!C50 + C11*0.02*(35.85/1024)*Assumptions!C51 -> 0.00058788396 | E82: =C50+C45 -> 3.5172307e-06 | F82: =C82+D82+E82+C54 -> 0.0018665477 | G82: =F82*12 -> 0.022398572
B83: 55 MB (avg video — iPhone 1080p mix) | C83: =(55/1024)*Assumptions!C55 -> 0.00080566406 | D83: =(55/1024)*Assumptions!C47 + (C11*0.02/10000)*Assumptions!C49 + C11*0.02*(55/1024)*Assumptions!C50 + C11*0.02*(55/1024)*Assumptions!C51 -> 0.00090187664 | E83: =C50+C45 -> 3.5172307e-06 | F83: =C83+D83+E83+C54 -> 0.0024610579 | G83: =F83*12 -> 0.029532695
B84: 100 MB (4K / H.264 heavy) | C84: =(100/1024)*Assumptions!C55 -> 0.0014648438 | D84: =(100/1024)*Assumptions!C47 + (C11*0.02/10000)*Assumptions!C49 + C11*0.02*(100/1024)*Assumptions!C50 + C11*0.02*(100/1024)*Assumptions!C51 -> 0.0016397184 | E84: =C50+C45 -> 3.5172307e-06 | F84: =C84+D84+E84+C54 -> 0.0038580794 | G84: =F84*12 -> 0.046296953
B85: 150 MB (max — 150 MB limit) | C85: =(150/1024)*Assumptions!C55 -> 0.0021972656 | D85: =(150/1024)*Assumptions!C47 + (C11*0.02/10000)*Assumptions!C49 + C11*0.02*(150/1024)*Assumptions!C50 + C11*0.02*(150/1024)*Assumptions!C51 -> 0.0024595427 | E85: =C50+C45 -> 3.5172307e-06 | F85: =C85+D85+E85+C54 -> 0.0054103255 | G85: =F85*12 -> 0.064923906

Sheet Revenue Recognition
B1: Revenue Recognition — Cash vs Hybrid vs Straight-Line
B2: Compares when revenue is recognized under each method + deferred revenue liability
C4: Month 1 | D4: Month 2 | E4: Month 3 | F4: Month 4 | G4: Month 5 | H4: Month 6 | I4: Month 7 | J4: Month 8 | K4: Month 9 | L4: Month 10 | M4: Month 11 | N4: Month 12 | O4: Month 13 | P4: Month 14 | Q4: Month 15 | R4: Month 16 | S4: Month 17 | T4: Month 18 | U4: Month 19 | V4: Month 20 | W4: Month 21 | X4: Month 22 | Y4: Month 23 | Z4: Month 24
B6: PER-CHARM REVENUE SPLIT — HYBRID METHOD | C6: 10-Year | D6: 15-Year | E6: Perpetual | F6: Lifetime months: | G6: 120 | H6: 180 | I6: 360
B7: Sale Price | C7: =Assumptions!C6 -> 29.99 | D7: =Assumptions!C7 -> 44.99 | E7: =Assumptions!C8 -> 69.99
B8: Upfront Costs (COGS + ship + processing + setup) | C8: =Assumptions!D6+Assumptions!C86+C7*Assumptions!C87+'Per-Charm Costs'!C24 -> 12.869748 | D8: =Assumptions!D7+Assumptions!C86+D7*Assumptions!C87+'Per-Charm Costs'!C24 -> 13.304748 | E8: =Assumptions!D8+Assumptions!C86+E7*Assumptions!C87+'Per-Charm Costs'!C24 -> 14.529748
B9: Hybrid: Revenue Recognized at Sale | C9: =C8 -> 12.869748 | D9: =D8 -> 13.304748 | E9: =E8 -> 14.529748 | F9: Covers COGS + fulfillment + payment fee + setup hosting
B10: Hybrid: Deferred Revenue (to escrow) | C10: =C7-C9 -> 17.120252 | D10: =D7-D9 -> 31.685252 | E10: =E7-E9 -> 55.460252 | F10: Goes to escrow / deferred revenue liability on balance sheet
B11: Hybrid: Monthly Recognition from Deferred | C11: =C10/G6 -> 0.14266877 | D11: =D10/H6 -> 0.17602918 | E11: =E10/I6 -> 0.15405626 | F11: Deferred portion ÷ lifetime months
B12: Straight-Line: Monthly Recognition (all deferred) | C12: =C7/G6 -> 0.24991667 | D12: =D7/H6 -> 0.24994444 | E12: =E7/I6 -> 0.19441667 | F12: Full price ÷ lifetime months — most conservative
B14: CASH COLLECTED (Point of Sale)
B15: 10-Year Charms — Cumulative Sold | C15: ='24-Month Projections'!C6 -> 100 | D15: =C15+'24-Month Projections'!D6 -> 208 | E15: =D15+'24-Month Projections'!E6 -> 325 | F15: =E15+'24-Month Projections'!F6 -> 451 | G15: =F15+'24-Month Projections'!G6 -> 587 | H15: =G15+'24-Month Projections'!H6 -> 734 | I15: =H15+'24-Month Projections'!I6 -> 893 | J15: =I15+'24-Month Projections'!J6 -> 1065 | K15: =J15+'24-Month Projections'!K6 -> 1251 | ... Z15: =Y15+'24-Month Projections'!Z6 -> 6719
B16: 15-Year Charms — Cumulative Sold | C16: ='24-Month Projections'!C7 -> 40 | D16: =C16+'24-Month Projections'!D7 -> 84 | E16: =D16+'24-Month Projections'!E7 -> 132 | F16: =E16+'24-Month Projections'!F7 -> 185 | G16: =F16+'24-Month Projections'!G7 -> 243 | H16: =G16+'24-Month Projections'!H7 -> 307 | I16: =H16+'24-Month Projections'!I7 -> 377 | J16: =I16+'24-Month Projections'!J7 -> 454 | K16: =J16+'24-Month Projections'!K7 -> 539 | ... Z16: =Y16+'24-Month Projections'!Z7 -> 3503
B17: Perpetual Charms — Cumulative Sold | C17: ='24-Month Projections'!C8 -> 15 | D17: =C17+'24-Month Projections'!D8 -> 32 | E17: =D17+'24-Month Projections'!E8 -> 51 | F17: =E17+'24-Month Projections'!F8 -> 72 | G17: =F17+'24-Month Projections'!G8 -> 96 | H17: =G17+'24-Month Projections'!H8 -> 123 | I17: =H17+'24-Month Projections'!I8 -> 153 | J17: =I17+'24-Month Projections'!J8 -> 187 | K17: =J17+'24-Month Projections'!K8 -> 225 | ... Z17: =Y17+'24-Month Projections'!Z8 -> 1813
B18: Charm Cash Collected (month) | C18: ='24-Month Projections'!C6*$C$7+'24-Month Projections'!C7*$D$7+'24-Month Projections'!C8*$E$7 -> 5848.45 | D18: ='24-Month Projections'!D6*$C$7+'24-Month Projections'!D7*$D$7+'24-Month Projections'!D8*$E$7 -> 6408.31 | E18: ='24-Month Projections'!E6*$C$7+'24-Month Projections'!E7*$D$7+'24-Month Projections'!E8*$E$7 -> 6998.16 | F18: ='24-Month Projections'!F6*$C$7+'24-Month Projections'!F7*$D$7+'24-Month Projections'!F8*$E$7 -> 7633 | G18: ='24-Month Projections'!G6*$C$7+'24-Month Projections'!G7*$D$7+'24-Month Projections'!G8*$E$7 -> 8367.82 | H18: ='24-Month Projections'!H6*$C$7+'24-Month Projections'!H7*$D$7+'24-Month Projections'!H8*$E$7 -> 9177.62 | I18: ='24-Month Projections'!I6*$C$7+'24-Month Projections'!I7*$D$7+'24-Month Projections'!I8*$E$7 -> 10017.41 | J18: ='24-Month Projections'!J6*$C$7+'24-Month Projections'!J7*$D$7+'24-Month Projections'!J8*$E$7 -> 11002.17 | ... Z18: ='24-Month Projections'!Z6*$C$7+'24-Month Projections'!Z7*$D$7+'24-Month Projections'!Z8*$E$7 -> 48268.45
B19: Upsell Cash Collected (recognized immediately) | C19: ='24-Month Projections'!C49+'24-Month Projections'!C50+'24-Month Projections'!C51 -> 199.72 | D19: ='24-Month Projections'!D49+'24-Month Projections'!D50+'24-Month Projections'!D51 -> 274.66 | E19: ='24-Month Projections'!E49+'24-Month Projections'!E50+'24-Month Projections'!E51 -> 389.57 | F19: ='24-Month Projections'!F49+'24-Month Projections'!F50+'24-Month Projections'!F51 -> 499.49 | G19: ='24-Month Projections'!G49+'24-Month Projections'!G50+'24-Month Projections'!G51 -> 629.39 | H19: ='24-Month Projections'!H49+'24-Month Projections'!H50+'24-Month Projections'!H51 -> 764.29 | I19: ='24-Month Projections'!I49+'24-Month Projections'!I50+'24-Month Projections'!I51 -> 894.19 | J19: ='24-Month Projections'!J49+'24-Month Projections'!J50+'24-Month Projections'!J51 -> 1059.07 | ... Z19: ='24-Month Projections'!Z49+'24-Month Projections'!Z50+'24-Month Projections'!Z51 -> 6874.66
B20: TOTAL CASH COLLECTED | C20: =C18+C19 -> 6048.17 | D20: =D18+D19 -> 6682.97 | E20: =E18+E19 -> 7387.73 | F20: =F18+F19 -> 8132.49 | G20: =G18+G19 -> 8997.21 | H20: =H18+H19 -> 9941.91 | I20: =I18+I19 -> 10911.6 | J20: =J18+J19 -> 12061.24 | ... Z20: =Z18+Z19 -> 55143.11
B22: HYBRID METHOD — Recognized Revenue | F22: COGS portion at sale + deferred over lifetime
B23: Upfront Recognition (new sales x upfront portion) | C23: ='24-Month Projections'!C6*$C$9+'24-Month Projections'!C7*$D$9+'24-Month Projections'!C8*$E$9 -> 2037.111 | D23: ='24-Month Projections'!D6*$C$9+'24-Month Projections'!D7*$D$9+'24-Month Projections'!D8*$E$9 -> 2222.3474 | E23: ='24-Month Projections'!E6*$C$9+'24-Month Projections'!E7*$D$9+'24-Month Projections'!E8*$E$9 -> 2420.4537 | F23: ='24-Month Projections'!F6*$C$9+'24-Month Projections'!F7*$D$9+'24-Month Projections'!F8*$E$9 -> 2631.8646 | G23: ='24-Month Projections'!G6*$C$9+'24-Month Projections'!G7*$D$9+'24-Month Projections'!G8*$E$9 -> 2870.6751 | H23: ='24-Month Projections'!H6*$C$9+'24-Month Projections'!H7*$D$9+'24-Month Projections'!H8*$E$9 -> 3135.6601 | I23: ='24-Month Projections'!I6*$C$9+'24-Month Projections'!I7*$D$9+'24-Month Projections'!I8*$E$9 -> 3413.5148 | J23: ='24-Month Projections'!J6*$C$9+'24-Month Projections'!J7*$D$9+'24-Month Projections'!J8*$E$9 -> 3732.0737 | ... Z23: ='24-Month Projections'!Z6*$C$9+'24-Month Projections'!Z7*$D$9+'24-Month Projections'!Z8*$E$9 -> 15363.829
B24: Deferred Recognition (cumulative charms x monthly rate) | C24: =C15*$C$11+C16*$D$11+C17*$E$11 -> 23.618887 | D24: =D15*$C$11+D16*$D$11+D17*$E$11 -> 49.391354 | E24: =E15*$C$11+E16*$D$11+E17*$E$11 -> 77.460069 | F24: =F15*$C$11+F16*$D$11+F17*$E$11 -> 108.00106 | G24: =G15*$C$11+G16*$D$11+G17*$E$11 -> 141.31106 | H24: =H15*$C$11+H16*$D$11+H17*$E$11 -> 177.70875 | I24: =I15*$C$11+I16*$D$11+I17*$E$11 -> 217.33681 | J24: =J15*$C$11+J16*$D$11+J17*$E$11 -> 260.668 | ... Z24: =Z15*$C$11+Z16*$D$11+Z17*$E$11 -> 1854.5256
B25: Upsell Revenue (immediate recognition) | C25: =C19 -> 199.72 | D25: =D19 -> 274.66 | E25: =E19 -> 389.57 | F25: =F19 -> 499.49 | G25: =G19 -> 629.39 | H25: =H19 -> 764.29 | I25: =I19 -> 894.19 | J25: =J19 -> 1059.07 | ... Z25: =Z19 -> 6874.66
B26: HYBRID RECOGNIZED REVENUE | C26: =C23+C24+C25 -> 2260.4499 | D26: =D23+D24+D25 -> 2546.3988 | E26: =E23+E24+E25 -> 2887.4837 | F26: =F23+F24+F25 -> 3239.3557 | G26: =G23+G24+G25 -> 3641.3762 | H26: =H23+H24+H25 -> 4077.6588 | I26: =I23+I24+I25 -> 4525.0416 | J26: =J23+J24+J25 -> 5051.8117 | ... Z26: =Z23+Z24+Z25 -> 24093.015
B28: STRAIGHT-LINE METHOD — Recognized Revenue | F28: Full price spread evenly over charm lifetime
B29: Charm Revenue (cumulative x monthly rate) | C29: =C15*$C$12+C16*$D$12+C17*$E$12 -> 37.905694 | D29: =D15*$C$12+D16*$D$12+D17*$E$12 -> 79.199333 | E29: =E15*$C$12+E16*$D$12+E17*$E$12 -> 124.13083 | F29: =F15*$C$12+F16*$D$12+F17*$E$12 -> 172.95014 | G29: =G15*$C$12+G16*$D$12+G17*$E$12 -> 226.10158 | H29: =H15*$C$12+H16*$D$12+H17*$E$12 -> 284.08503 | I29: =I15*$C$12+I16*$D$12+I17*$E$12 -> 347.15039 | J29: =J15*$C$12+J16*$D$12+J17*$E$12 -> 415.99194 | ... Z29: =Z15*$C$12+Z16*$D$12+Z17*$E$12 -> 2907.2229
B30: Upsell Revenue (immediate recognition) | C30: =C19 -> 199.72 | D30: =D19 -> 274.66 | E30: =E19 -> 389.57 | F30: =F19 -> 499.49 | G30: =G19 -> 629.39 | H30: =H19 -> 764.29 | I30: =I19 -> 894.19 | J30: =J19 -> 1059.07 | ... Z30: =Z19 -> 6874.66
B31: STRAIGHT-LINE RECOGNIZED REVENUE | C31: =C29+C30 -> 237.62569 | D31: =D29+D30 -> 353.85933 | E31: =E29+E30 -> 513.70083 | F31: =F29+F30 -> 672.44014 | G31: =G29+G30 -> 855.49158 | H31: =H29+H30 -> 1048.375 | I31: =I29+I30 -> 1241.3404 | J31: =J29+J30 -> 1475.0619 | ... Z31: =Z29+Z30 -> 9781.8829
B33: SIDE-BY-SIDE COMPARISON
B34: Cash Collected | C34: =C20 -> 6048.17 | D34: =D20 -> 6682.97 | E34: =E20 -> 7387.73 | F34: =F20 -> 8132.49 | G34: =G20 -> 8997.21 | H34: =H20 -> 9941.91 | I34: =I20 -> 10911.6 | J34: =J20 -> 12061.24 | ... Z34: =Z20 -> 55143.11
B35: Hybrid Recognized | C35: =C26 -> 2260.4499 | D35: =D26 -> 2546.3988 | E35: =E26 -> 2887.4837 | F35: =F26 -> 3239.3557 | G35: =G26 -> 3641.3762 | H35: =H26 -> 4077.6588 | I35: =I26 -> 4525.0416 | J35: =J26 -> 5051.8117 | ... Z35: =Z26 -> 24093.015
B36: Straight-Line Recognized | C36: =C31 -> 237.62569 | D36: =D31 -> 353.85933 | E36: =E31 -> 513.70083 | F36: =F31 -> 672.44014 | G36: =G31 -> 855.49158 | H36: =H31 -> 1048.375 | I36: =I31 -> 1241.3404 | J36: =J31 -> 1475.0619 | ... Z36: =Z31 -> 9781.8829
B37: Cash vs Hybrid Gap (unrecognized cash) | C37: =C34-C35 -> 3787.7201 | D37: =D34-D35 -> 4136.5712 | E37: =E34-E35 -> 4500.2463 | F37: =F34-F35 -> 4893.1343 | G37: =G34-G35 -> 5355.8338 | H37: =H34-H35 -> 5864.2512 | I37: =I34-I35 -> 6386.5584 | J37: =J34-J35 -> 7009.4283 | ... Z37: =Z34-Z35 -> 31050.095
B38: Cash vs Straight-Line Gap (unrecognized cash) | C38: =C34-C36 -> 5810.5443 | D38: =D34-D36 -> 6329.1107 | E38: =E34-E36 -> 6874.0292 | F38: =F34-F36 -> 7460.0499 | G38: =G34-G36 -> 8141.7184 | H38: =H34-H36 -> 8893.535 | I38: =I34-I36 -> 9670.2596 | J38: =J34-J36 -> 10586.178 | ... Z38: =Z34-Z36 -> 45361.227
B40: DEFERRED REVENUE LIABILITY (Balance Sheet) | F40: This is your escrow — cash received but not yet earned
B42: HYBRID — Deferred Revenue Balance | F42: Opening + new deferrals - monthly recognition = closing
B43: + New Deferrals (charm sales x deferred portion) | C43: ='24-Month Projections'!C6*$C$10+'24-Month Projections'!C7*$D$10+'24-Month Projections'!C8*$E$10 -> 3811.339 | D43: ='24-Month Projections'!D6*$C$10+'24-Month Projections'!D7*$D$10+'24-Month Projections'!D8*$E$10 -> 4185.9626 | E43: ='24-Month Projections'!E6*$C$10+'24-Month Projections'!E7*$D$10+'24-Month Projections'!E8*$E$10 -> 4577.7063 | F43: ='24-Month Projections'!F6*$C$10+'24-Month Projections'!F7*$D$10+'24-Month Projections'!F8*$E$10 -> 5001.1354 | G43: ='24-Month Projections'!G6*$C$10+'24-Month Projections'!G7*$D$10+'24-Month Projections'!G8*$E$10 -> 5497.1449 | H43: ='24-Month Projections'!H6*$C$10+'24-Month Projections'!H7*$D$10+'24-Month Projections'!H8*$E$10 -> 6041.9599 | I43: ='24-Month Projections'!I6*$C$10+'24-Month Projections'!I7*$D$10+'24-Month Projections'!I8*$E$10 -> 6603.8952 | J43: ='24-Month Projections'!J6*$C$10+'24-Month Projections'!J7*$D$10+'24-Month Projections'!J8*$E$10 -> 7270.0963 | ... Z43: ='24-Month Projections'!Z6*$C$10+'24-Month Projections'!Z7*$D$10+'24-Month Projections'!Z8*$E$10 -> 32904.621
B44: - Monthly Recognition (from deferred pool) | C44: =C24 -> 23.618887 | D44: =D24 -> 49.391354 | E44: =E24 -> 77.460069 | F44: =F24 -> 108.00106 | G44: =G24 -> 141.31106 | H44: =H24 -> 177.70875 | I44: =I24 -> 217.33681 | J44: =J24 -> 260.668 | ... Z44: =Z24 -> 1854.5256
B45: - Return Reversals (refunded charms x deferred portion) | C45: =IF('24-Month Projections'!C9>0, '24-Month Projections'!C88*(C43/'24-Month Projections'!C9), 0) -> 221.30356 | D45: =IF('24-Month Projections'!D9>0, '24-Month Projections'!D88*(D43/'24-Month Projections'!D9), 0) -> 247.69009 | E45: =IF('24-Month Projections'!E9>0, '24-Month Projections'!E88*(E43/'24-Month Projections'!E9), 0) -> 273.66723 | F45: =IF('24-Month Projections'!F9>0, '24-Month Projections'!F88*(F43/'24-Month Projections'!F9), 0) -> 300.06812 | G45: =IF('24-Month Projections'!G9>0, '24-Month Projections'!G88*(G43/'24-Month Projections'!G9), 0) -> 327.81139 | H45: =IF('24-Month Projections'!H9>0, '24-Month Projections'!H88*(H43/'24-Month Projections'!H9), 0) -> 355.40941 | I45: =IF('24-Month Projections'!I9>0, '24-Month Projections'!I88*(I43/'24-Month Projections'!I9), 0) -> 407.96264 | J45: =IF('24-Month Projections'!J9>0, '24-Month Projections'!J88*(J43/'24-Month Projections'!J9), 0) -> 436.71956 | ... Z45: =IF('24-Month Projections'!Z9>0, '24-Month Projections'!Z88*(Z43/'24-Month Projections'!Z9), 0) -> 1965.7306
B46: = HYBRID Deferred Revenue Balance | C46: =C43-C44-C45 -> 3566.4166 | D46: =C46+D43-D44-D45 -> 7455.2977 | E46: =D46+E43-E44-E45 -> 11681.877 | F46: =E46+F43-F44-F45 -> 16274.943 | G46: =F46+G43-G44-G45 -> 21302.965 | H46: =G46+H43-H44-H45 -> 26811.807 | I46: =H46+I43-I44-I45 -> 32790.403 | J46: =I46+J43-J44-J45 -> 39363.112 | K46: =J46+K43-K44-K45 -> 46549.2 | ... Z46: =Y46+Z43-Z44-Z45 -> 291145.54
B48: STRAIGHT-LINE — Deferred Revenue Balance
B49: + New Deferrals (full charm price) | C49: ='24-Month Projections'!C6*$C$7+'24-Month Projections'!C7*$D$7+'24-Month Projections'!C8*$E$7 -> 5848.45 | D49: ='24-Month Projections'!D6*$C$7+'24-Month Projections'!D7*$D$7+'24-Month Projections'!D8*$E$7 -> 6408.31 | E49: ='24-Month Projections'!E6*$C$7+'24-Month Projections'!E7*$D$7+'24-Month Projections'!E8*$E$7 -> 6998.16 | F49: ='24-Month Projections'!F6*$C$7+'24-Month Projections'!F7*$D$7+'24-Month Projections'!F8*$E$7 -> 7633 | G49: ='24-Month Projections'!G6*$C$7+'24-Month Projections'!G7*$D$7+'24-Month Projections'!G8*$E$7 -> 8367.82 | H49: ='24-Month Projections'!H6*$C$7+'24-Month Projections'!H7*$D$7+'24-Month Projections'!H8*$E$7 -> 9177.62 | I49: ='24-Month Projections'!I6*$C$7+'24-Month Projections'!I7*$D$7+'24-Month Projections'!I8*$E$7 -> 10017.41 | J49: ='24-Month Projections'!J6*$C$7+'24-Month Projections'!J7*$D$7+'24-Month Projections'!J8*$E$7 -> 11002.17 | ... Z49: ='24-Month Projections'!Z6*$C$7+'24-Month Projections'!Z7*$D$7+'24-Month Projections'!Z8*$E$7 -> 48268.45
B50: - Monthly Recognition | C50: =C29 -> 37.905694 | D50: =D29 -> 79.199333 | E50: =E29 -> 124.13083 | F50: =F29 -> 172.95014 | G50: =G29 -> 226.10158 | H50: =H29 -> 284.08503 | I50: =I29 -> 347.15039 | J50: =J29 -> 415.99194 | ... Z50: =Z29 -> 2907.2229
B51: - Return Reversals (refunded charms x full price) | C51: =IF('24-Month Projections'!C9>0, '24-Month Projections'!C88*(C49/'24-Month Projections'!C9), 0) -> 339.58742 | D51: =IF('24-Month Projections'!D9>0, '24-Month Projections'!D88*(D49/'24-Month Projections'!D9), 0) -> 379.18994 | E51: =IF('24-Month Projections'!E9>0, '24-Month Projections'!E88*(E49/'24-Month Projections'!E9), 0) -> 418.36826 | F51: =IF('24-Month Projections'!F9>0, '24-Month Projections'!F88*(F49/'24-Month Projections'!F9), 0) -> 457.98 | G51: =IF('24-Month Projections'!G9>0, '24-Month Projections'!G88*(G49/'24-Month Projections'!G9), 0) -> 498.99844 | H51: =IF('24-Month Projections'!H9>0, '24-Month Projections'!H88*(H49/'24-Month Projections'!H9), 0) -> 539.86 | I51: =IF('24-Month Projections'!I9>0, '24-Month Projections'!I88*(I49/'24-Month Projections'!I9), 0) -> 618.83614 | J51: =IF('24-Month Projections'!J9>0, '24-Month Projections'!J88*(J49/'24-Month Projections'!J9), 0) -> 660.90774 | ... Z51: =IF('24-Month Projections'!Z9>0, '24-Month Projections'!Z88*(Z49/'24-Month Projections'!Z9), 0) -> 2883.5697
B52: = STRAIGHT-LINE Deferred Revenue Balance | C52: =C49-C50-C51 -> 5470.9569 | D52: =C52+D49-D50-D51 -> 11420.878 | E52: =D52+E49-E50-E51 -> 17876.539 | F52: =E52+F49-F50-F51 -> 24878.608 | G52: =F52+G49-G50-G51 -> 32521.328 | H52: =G52+H49-H50-H51 -> 40875.003 | I52: =H52+I49-I50-I51 -> 49926.427 | J52: =I52+J49-J50-J51 -> 59851.697 | K52: =J52+K49-K50-K51 -> 70680.827 | ... Z52: =Y52+Z49-Z50-Z51 -> 431832.02
B54: EBITDA UNDER EACH RECOGNITION METHOD (incl. returns) | F54: Uses adjusted costs (COGS + returns + OpEx)
B55: Adjusted Total Costs (COGS + returns + OpEx) | C55: ='24-Month Projections'!C105+'24-Month Projections'!C106+'24-Month Projections'!C70 -> 3080.9394 | D55: ='24-Month Projections'!D105+'24-Month Projections'!D106+'24-Month Projections'!D70 -> 3305.955 | E55: ='24-Month Projections'!E105+'24-Month Projections'!E106+'24-Month Projections'!E70 -> 3561.4379 | F55: ='24-Month Projections'!F105+'24-Month Projections'!F106+'24-Month Projections'!F70 -> 3834.1298 | G55: ='24-Month Projections'!G105+'24-Month Projections'!G106+'24-Month Projections'!G70 -> 4135.7879 | H55: ='24-Month Projections'!H105+'24-Month Projections'!H106+'24-Month Projections'!H70 -> 4467.8605 | I55: ='24-Month Projections'!I105+'24-Month Projections'!I106+'24-Month Projections'!I70 -> 4811.4192 | J55: ='24-Month Projections'!J105+'24-Month Projections'!J106+'24-Month Projections'!J70 -> 5203.9942 | ... Z55: ='24-Month Projections'!Z105+'24-Month Projections'!Z106+'24-Month Projections'!Z70 -> 19120.4
B56: Cash Basis EBITDA (after returns) | C56: ='24-Month Projections'!C104-C55 -> 2616.0465 | D56: ='24-Month Projections'!D104-D55 -> 2981.573 | E56: ='24-Month Projections'!E104-E55 -> 3384.6343 | F56: ='24-Month Projections'!F104-F55 -> 3810.4108 | G56: ='24-Month Projections'!G104-G55 -> 4324.8913 | H56: ='24-Month Projections'!H104-H55 -> 4889.2313 | I56: ='24-Month Projections'!I104-I55 -> 5426.1052 | J56: ='24-Month Projections'!J104-J55 -> 6132.719 | ... Z56: ='24-Month Projections'!Z104-Z55 -> 32728.446
B57: Hybrid EBITDA (after returns) | C57: =C26-'24-Month Projections'!C94-C55 -> -1171.6736 | D57: =D26-'24-Month Projections'!D94-D55 -> -1154.9982 | E57: =E26-'24-Month Projections'!E94-E55 -> -1115.6119 | F57: =F26-'24-Month Projections'!F94-F55 -> -1082.7235 | G57: =G26-'24-Month Projections'!G94-G55 -> -1030.9426 | H57: =H26-'24-Month Projections'!H94-H55 -> -975.01989 | I57: =I26-'24-Month Projections'!I94-I55 -> -960.45324 | J57: =J26-'24-Month Projections'!J94-J55 -> -876.70928 | ... Z57: =Z26-'24-Month Projections'!Z94-Z55 -> 1678.3508
B58: Straight-Line EBITDA (after returns) | C58: =C31-'24-Month Projections'!C94-C55 -> -3194.4978 | D58: =D31-'24-Month Projections'!D94-D55 -> -3347.5376 | E58: =E31-'24-Month Projections'!E94-E55 -> -3489.3948 | F58: =F31-'24-Month Projections'!F94-F55 -> -3649.6391 | G58: =G31-'24-Month Projections'!G94-G55 -> -3816.8272 | H58: =H31-'24-Month Projections'!H94-H55 -> -4004.3037 | I58: =I31-'24-Month Projections'!I94-I55 -> -4244.1544 | J58: =J31-'24-Month Projections'!J94-J55 -> -4453.4591 | ... Z58: =Z31-'24-Month Projections'!Z94-Z55 -> -12632.781
B60: ESCROW HEALTH — Can deferred revenue cover future hosting?
B61: Est. Future Hosting Obligation (net active charms x monthly cost x lifetime) | C61: =(C15*'Per-Charm Costs'!C56*$G$6 + C16*'Per-Charm Costs'!C56*$H$6 + C17*'Per-Charm Costs'!C56*$I$6) -> 46.138995 | D61: =(D15*'Per-Charm Costs'!C56*$G$6 + D16*'Per-Charm Costs'!C56*$H$6 + D17*'Per-Charm Costs'!C56*$I$6) -> 96.779356 | E61: =(E15*'Per-Charm Costs'!C56*$G$6 + E16*'Per-Charm Costs'!C56*$H$6 + E17*'Per-Charm Costs'!C56*$I$6) -> 152.14615 | F61: =(F15*'Per-Charm Costs'!C56*$G$6 + F16*'Per-Charm Costs'!C56*$H$6 + F17*'Per-Charm Costs'!C56*$I$6) -> 212.57698 | G61: =(G15*'Per-Charm Costs'!C56*$G$6 + G16*'Per-Charm Costs'!C56*$H$6 + G17*'Per-Charm Costs'!C56*$I$6) -> 278.97212 | H61: =(H15*'Per-Charm Costs'!C56*$G$6 + H16*'Per-Charm Costs'!C56*$H$6 + H17*'Per-Charm Costs'!C56*$I$6) -> 351.89424 | I61: =(I15*'Per-Charm Costs'!C56*$G$6 + I16*'Per-Charm Costs'!C56*$H$6 + I17*'Per-Charm Costs'!C56*$I$6) -> 431.56841 | J61: =(J15*'Per-Charm Costs'!C56*$G$6 + J16*'Per-Charm Costs'!C56*$H$6 + J17*'Per-Charm Costs'!C56*$I$6) -> 519.2325 | K61: =(K15*'Per-Charm Costs'!C56*$G$6 + K16*'Per-Charm Costs'!C56*$H$6 + K17*'Per-Charm Costs'!C56*$I$6) -> 615.44918 | L61: =(L15*'Per-Charm Costs'!C56*$G$6 + L16*'Per-Charm Costs'!C56*$H$6 + L17*'Per-Charm Costs'!C56*$I$6) -> 721.45634 | M61: =(M15*'Per-Charm Costs'!C56*$G$6 + M16*'Per-Charm Costs'!C56*$H$6 + M17*'Per-Charm Costs'!C56*$I$6) -> 837.47903 | N61: =(N15*'Per-Charm Costs'!C56*$G$6 + N16*'Per-Charm Costs'!C56*$H$6 + N17*'Per-Charm Costs'!C56*$I$6) -> 964.75514 | O61: =(O15*'Per-Charm Costs'!C56*$G$6 + O16*'Per-Charm Costs'!C56*$H$6 + O17*'Per-Charm Costs'!C56*$I$6) -> 1104.0724 | P61: =(P15*'Per-Charm Costs'!C56*$G$6 + P16*'Per-Charm Costs'!C56*$H$6 + P17*'Per-Charm Costs'!C56*$I$6) -> 1256.6687 | Q61: =(Q15*'Per-Charm Costs'!C56*$G$6 + Q16*'Per-Charm Costs'!C56*$H$6 + Q17*'Per-Charm Costs'!C56*$I$6) -> 1424.3445 | R61: =(R15*'Per-Charm Costs'!C56*$G$6 + R16*'Per-Charm Costs'!C56*$H$6 + R17*'Per-Charm Costs'!C56*$I$6) -> 1608.5629 | S61: =(S15*'Per-Charm Costs'!C56*$G$6 + S16*'Per-Charm Costs'!C56*$H$6 + S17*'Per-Charm Costs'!C56*$I$6) -> 1811.1244 | T61: =(T15*'Per-Charm Costs'!C56*$G$6 + T16*'Per-Charm Costs'!C56*$H$6 + T17*'Per-Charm Costs'!C56*$I$6) -> 2033.4918 | U61: =(U15*'Per-Charm Costs'!C56*$G$6 + U16*'Per-Charm Costs'!C56*$H$6 + U17*'Per-Charm Costs'!C56*$I$6) -> 2278.141 | V61: =(V15*'Per-Charm Costs'!C56*$G$6 + V16*'Per-Charm Costs'!C56*$H$6 + V17*'Per-Charm Costs'!C56*$I$6) -> 2546.8725 | W61: =(W15*'Per-Charm Costs'!C56*$G$6 + W16*'Per-Charm Costs'!C56*$H$6 + W17*'Per-Charm Costs'!C56*$I$6) -> 2842.3872 | X61: =(X15*'Per-Charm Costs'!C56*$G$6 + X16*'Per-Charm Costs'!C56*$H$6 + X17*'Per-Charm Costs'!C56*$I$6) -> 3167.7234 | Y61: =(Y15*'Per-Charm Costs'!C56*$G$6 + Y16*'Per-Charm Costs'!C56*$H$6 + Y17*'Per-Charm Costs'!C56*$I$6) -> 3525.5819 | Z61: =(Z15*'Per-Charm Costs'!C56*$G$6 + Z16*'Per-Charm Costs'!C56*$H$6 + Z17*'Per-Charm Costs'!C56*$I$6) -> 3919.0012
B62: Hybrid Deferred Revenue Balance (escrow pool) | C62: =C46 -> 3566.4166 | D62: =D46 -> 7455.2977 | E62: =E46 -> 11681.877 | F62: =F46 -> 16274.943 | G62: =G46 -> 21302.965 | H62: =H46 -> 26811.807 | I62: =I46 -> 32790.403 | J62: =J46 -> 39363.112 | ... Z62: =Z46 -> 291145.54
B63: COVERAGE RATIO (deferred balance / hosting obligation) | C63: =IF(C61>0,C62/C61,0) -> 77.297231 | D63: =IF(D61>0,D62/D61,0) -> 77.033967 | E63: =IF(E61>0,E62/E61,0) -> 76.780627 | F63: > 100% = escrow covers all future hosting. < 100% = shortfall risk. | G63: =IF(G61>0,G62/G61,0) -> 76.362345 | H63: =IF(H61>0,H62/H61,0) -> 76.192799 | I63: =IF(I61>0,I62/I61,0) -> 75.979619 | J63: =IF(J61>0,J62/J61,0) -> 75.810185 | K63: =IF(K61>0,K62/K61,0) -> 75.634514 | L63: =IF(L61>0,L62/L61,0) -> 75.503859 | M63: =IF(M61>0,M62/M61,0) -> 75.370009 | N63: =IF(N61>0,N62/N61,0) -> 75.242903 | ... Z63: =IF(Z61>0,Z62/Z61,0) -> 74.29075
